<?xml version="1.0" encoding="UTF-8"?>
<mxfile host="app.diagrams.net" agent="Mozilla/5.0 (Windows NT 10.0; Win64; x64) AppleWebKit/537.36 (KHTML, like Gecko) Chrome/137.0.0.0 Safari/537.36" version="27.1.6">
  <diagram name="Page-1" id="3fHMSD_8ZNjlqIWDcTgF">
    <mxGraphModel dx="4884" dy="2723" grid="1" gridSize="10" guides="1" tooltips="1" connect="1" arrows="1" fold="1" page="1" pageScale="1" pageWidth="850" pageHeight="1100" math="0" shadow="0">
      <root>
        <mxCell id="0" />
        <mxCell id="1" parent="0" />
        <mxCell id="2embDGzhRkxAqKEgTfxS-55" style="edgeStyle=orthogonalEdgeStyle;rounded=0;orthogonalLoop=1;jettySize=auto;html=1;exitX=1;exitY=0.3333333333333333;exitDx=0;exitDy=0;exitPerimeter=0;entryX=0.5;entryY=1;entryDx=0;entryDy=0;" edge="1" parent="1" source="2embDGzhRkxAqKEgTfxS-7" target="2embDGzhRkxAqKEgTfxS-54">
          <mxGeometry relative="1" as="geometry" />
        </mxCell>
        <mxCell id="2embDGzhRkxAqKEgTfxS-56" style="edgeStyle=orthogonalEdgeStyle;rounded=0;orthogonalLoop=1;jettySize=auto;html=1;exitX=0;exitY=0.3333333333333333;exitDx=0;exitDy=0;exitPerimeter=0;entryX=1;entryY=0.5;entryDx=0;entryDy=0;" edge="1" parent="1" source="2embDGzhRkxAqKEgTfxS-7" target="2embDGzhRkxAqKEgTfxS-10">
          <mxGeometry relative="1" as="geometry" />
        </mxCell>
        <mxCell id="2embDGzhRkxAqKEgTfxS-61" style="edgeStyle=orthogonalEdgeStyle;rounded=0;orthogonalLoop=1;jettySize=auto;html=1;exitX=0;exitY=1;exitDx=0;exitDy=0;exitPerimeter=0;entryX=0.5;entryY=0;entryDx=0;entryDy=0;" edge="1" parent="1" source="2embDGzhRkxAqKEgTfxS-7" target="2embDGzhRkxAqKEgTfxS-8">
          <mxGeometry relative="1" as="geometry" />
        </mxCell>
        <mxCell id="2embDGzhRkxAqKEgTfxS-62" style="edgeStyle=orthogonalEdgeStyle;rounded=0;orthogonalLoop=1;jettySize=auto;html=1;exitX=1;exitY=1;exitDx=0;exitDy=0;exitPerimeter=0;entryX=0.5;entryY=0;entryDx=0;entryDy=0;" edge="1" parent="1" source="2embDGzhRkxAqKEgTfxS-7" target="2embDGzhRkxAqKEgTfxS-9">
          <mxGeometry relative="1" as="geometry" />
        </mxCell>
        <mxCell id="2embDGzhRkxAqKEgTfxS-7" value="Visitor" style="shape=umlActor;verticalLabelPosition=bottom;verticalAlign=top;html=1;" vertex="1" parent="1">
          <mxGeometry x="130" y="205" width="30" height="60" as="geometry" />
        </mxCell>
        <mxCell id="2embDGzhRkxAqKEgTfxS-8" value="Watch artworks" style="ellipse;whiteSpace=wrap;html=1;" vertex="1" parent="1">
          <mxGeometry x="-90" y="350" width="140" height="70" as="geometry" />
        </mxCell>
        <mxCell id="2embDGzhRkxAqKEgTfxS-9" value="Watch artist profile" style="ellipse;whiteSpace=wrap;html=1;" vertex="1" parent="1">
          <mxGeometry x="200" y="340" width="140" height="70" as="geometry" />
        </mxCell>
        <mxCell id="2embDGzhRkxAqKEgTfxS-10" value="Register" style="ellipse;whiteSpace=wrap;html=1;" vertex="1" parent="1">
          <mxGeometry x="-90" y="190" width="140" height="70" as="geometry" />
        </mxCell>
        <mxCell id="2embDGzhRkxAqKEgTfxS-26" style="edgeStyle=orthogonalEdgeStyle;rounded=0;orthogonalLoop=1;jettySize=auto;html=1;exitX=1;exitY=1;exitDx=0;exitDy=0;exitPerimeter=0;" edge="1" parent="1" source="2embDGzhRkxAqKEgTfxS-14" target="2embDGzhRkxAqKEgTfxS-23">
          <mxGeometry relative="1" as="geometry" />
        </mxCell>
        <mxCell id="2embDGzhRkxAqKEgTfxS-28" style="edgeStyle=orthogonalEdgeStyle;rounded=0;orthogonalLoop=1;jettySize=auto;html=1;exitX=0;exitY=0.3333333333333333;exitDx=0;exitDy=0;exitPerimeter=0;entryX=1;entryY=0.5;entryDx=0;entryDy=0;" edge="1" parent="1" source="2embDGzhRkxAqKEgTfxS-14" target="2embDGzhRkxAqKEgTfxS-27">
          <mxGeometry relative="1" as="geometry" />
        </mxCell>
        <mxCell id="2embDGzhRkxAqKEgTfxS-29" style="edgeStyle=orthogonalEdgeStyle;rounded=0;orthogonalLoop=1;jettySize=auto;html=1;exitX=1;exitY=0.3333333333333333;exitDx=0;exitDy=0;exitPerimeter=0;entryX=0;entryY=0.5;entryDx=0;entryDy=0;" edge="1" parent="1" source="2embDGzhRkxAqKEgTfxS-14" target="2embDGzhRkxAqKEgTfxS-19">
          <mxGeometry relative="1" as="geometry" />
        </mxCell>
        <mxCell id="2embDGzhRkxAqKEgTfxS-36" style="edgeStyle=orthogonalEdgeStyle;rounded=0;orthogonalLoop=1;jettySize=auto;html=1;exitX=0.75;exitY=0.1;exitDx=0;exitDy=0;exitPerimeter=0;entryX=0.5;entryY=1;entryDx=0;entryDy=0;" edge="1" parent="1" source="2embDGzhRkxAqKEgTfxS-14" target="2embDGzhRkxAqKEgTfxS-35">
          <mxGeometry relative="1" as="geometry" />
        </mxCell>
        <mxCell id="2embDGzhRkxAqKEgTfxS-59" style="edgeStyle=orthogonalEdgeStyle;rounded=0;orthogonalLoop=1;jettySize=auto;html=1;exitX=0.5;exitY=0;exitDx=0;exitDy=0;exitPerimeter=0;entryX=0.5;entryY=1;entryDx=0;entryDy=0;" edge="1" parent="1" source="2embDGzhRkxAqKEgTfxS-14" target="2embDGzhRkxAqKEgTfxS-16">
          <mxGeometry relative="1" as="geometry" />
        </mxCell>
        <mxCell id="2embDGzhRkxAqKEgTfxS-60" style="edgeStyle=orthogonalEdgeStyle;rounded=0;orthogonalLoop=1;jettySize=auto;html=1;exitX=0;exitY=1;exitDx=0;exitDy=0;exitPerimeter=0;entryX=0.5;entryY=0;entryDx=0;entryDy=0;" edge="1" parent="1" source="2embDGzhRkxAqKEgTfxS-14" target="2embDGzhRkxAqKEgTfxS-15">
          <mxGeometry relative="1" as="geometry" />
        </mxCell>
        <mxCell id="2embDGzhRkxAqKEgTfxS-14" value="User (Logged in)" style="shape=umlActor;verticalLabelPosition=bottom;verticalAlign=top;html=1;" vertex="1" parent="1">
          <mxGeometry x="505" y="220" width="30" height="60" as="geometry" />
        </mxCell>
        <mxCell id="2embDGzhRkxAqKEgTfxS-15" value="Login" style="ellipse;whiteSpace=wrap;html=1;" vertex="1" parent="1">
          <mxGeometry x="370" y="350" width="140" height="70" as="geometry" />
        </mxCell>
        <mxCell id="2embDGzhRkxAqKEgTfxS-53" style="edgeStyle=orthogonalEdgeStyle;rounded=0;orthogonalLoop=1;jettySize=auto;html=1;entryX=0.5;entryY=1;entryDx=0;entryDy=0;" edge="1" parent="1" source="2embDGzhRkxAqKEgTfxS-16" target="2embDGzhRkxAqKEgTfxS-49">
          <mxGeometry relative="1" as="geometry" />
        </mxCell>
        <mxCell id="2embDGzhRkxAqKEgTfxS-16" value="Write comments" style="ellipse;whiteSpace=wrap;html=1;" vertex="1" parent="1">
          <mxGeometry x="450" y="60" width="140" height="60" as="geometry" />
        </mxCell>
        <mxCell id="2embDGzhRkxAqKEgTfxS-52" style="edgeStyle=orthogonalEdgeStyle;rounded=0;orthogonalLoop=1;jettySize=auto;html=1;exitX=1;exitY=0.5;exitDx=0;exitDy=0;entryX=0;entryY=0.5;entryDx=0;entryDy=0;" edge="1" parent="1" source="2embDGzhRkxAqKEgTfxS-19" target="2embDGzhRkxAqKEgTfxS-51">
          <mxGeometry relative="1" as="geometry" />
        </mxCell>
        <mxCell id="2embDGzhRkxAqKEgTfxS-19" value="Like artworks" style="ellipse;whiteSpace=wrap;html=1;" vertex="1" parent="1">
          <mxGeometry x="700" y="205" width="140" height="70" as="geometry" />
        </mxCell>
        <mxCell id="2embDGzhRkxAqKEgTfxS-64" style="edgeStyle=orthogonalEdgeStyle;rounded=0;orthogonalLoop=1;jettySize=auto;html=1;exitX=1;exitY=0.5;exitDx=0;exitDy=0;entryX=0;entryY=0.5;entryDx=0;entryDy=0;" edge="1" parent="1" source="2embDGzhRkxAqKEgTfxS-23" target="2embDGzhRkxAqKEgTfxS-63">
          <mxGeometry relative="1" as="geometry" />
        </mxCell>
        <mxCell id="2embDGzhRkxAqKEgTfxS-23" value="Start a conversation with an artist" style="ellipse;whiteSpace=wrap;html=1;" vertex="1" parent="1">
          <mxGeometry x="535" y="350" width="140" height="70" as="geometry" />
        </mxCell>
        <mxCell id="2embDGzhRkxAqKEgTfxS-27" value="manage personnal informations" style="ellipse;whiteSpace=wrap;html=1;" vertex="1" parent="1">
          <mxGeometry x="340" y="205" width="140" height="70" as="geometry" />
        </mxCell>
        <mxCell id="2embDGzhRkxAqKEgTfxS-37" style="edgeStyle=orthogonalEdgeStyle;rounded=0;orthogonalLoop=1;jettySize=auto;html=1;exitX=1;exitY=0.3333333333333333;exitDx=0;exitDy=0;exitPerimeter=0;entryX=0;entryY=0.5;entryDx=0;entryDy=0;" edge="1" parent="1" source="2embDGzhRkxAqKEgTfxS-30" target="2embDGzhRkxAqKEgTfxS-34">
          <mxGeometry relative="1" as="geometry" />
        </mxCell>
        <mxCell id="2embDGzhRkxAqKEgTfxS-40" style="edgeStyle=orthogonalEdgeStyle;rounded=0;orthogonalLoop=1;jettySize=auto;html=1;exitX=0;exitY=0.3333333333333333;exitDx=0;exitDy=0;exitPerimeter=0;" edge="1" parent="1" source="2embDGzhRkxAqKEgTfxS-30" target="2embDGzhRkxAqKEgTfxS-38">
          <mxGeometry relative="1" as="geometry" />
        </mxCell>
        <mxCell id="2embDGzhRkxAqKEgTfxS-73" style="edgeStyle=orthogonalEdgeStyle;rounded=0;orthogonalLoop=1;jettySize=auto;html=1;exitX=0.5;exitY=0;exitDx=0;exitDy=0;exitPerimeter=0;entryX=0.5;entryY=1;entryDx=0;entryDy=0;" edge="1" parent="1" source="2embDGzhRkxAqKEgTfxS-30" target="2embDGzhRkxAqKEgTfxS-67">
          <mxGeometry relative="1" as="geometry" />
        </mxCell>
        <mxCell id="2embDGzhRkxAqKEgTfxS-30" value="Artist" style="shape=umlActor;verticalLabelPosition=bottom;verticalAlign=top;html=1;" vertex="1" parent="1">
          <mxGeometry x="130" y="620" width="30" height="60" as="geometry" />
        </mxCell>
        <mxCell id="2embDGzhRkxAqKEgTfxS-72" style="edgeStyle=orthogonalEdgeStyle;rounded=0;orthogonalLoop=1;jettySize=auto;html=1;exitX=0.5;exitY=0;exitDx=0;exitDy=0;entryX=0.5;entryY=1;entryDx=0;entryDy=0;" edge="1" parent="1" source="2embDGzhRkxAqKEgTfxS-34" target="2embDGzhRkxAqKEgTfxS-71">
          <mxGeometry relative="1" as="geometry" />
        </mxCell>
        <mxCell id="2embDGzhRkxAqKEgTfxS-34" value="answer conversations" style="ellipse;whiteSpace=wrap;html=1;" vertex="1" parent="1">
          <mxGeometry x="230" y="605" width="140" height="70" as="geometry" />
        </mxCell>
        <mxCell id="2embDGzhRkxAqKEgTfxS-66" style="edgeStyle=orthogonalEdgeStyle;rounded=0;orthogonalLoop=1;jettySize=auto;html=1;exitX=1;exitY=0.5;exitDx=0;exitDy=0;entryX=0;entryY=0.5;entryDx=0;entryDy=0;" edge="1" parent="1" source="2embDGzhRkxAqKEgTfxS-35" target="2embDGzhRkxAqKEgTfxS-65">
          <mxGeometry relative="1" as="geometry" />
        </mxCell>
        <mxCell id="2embDGzhRkxAqKEgTfxS-35" value="Initiate order" style="ellipse;whiteSpace=wrap;html=1;" vertex="1" parent="1">
          <mxGeometry x="540" y="120" width="140" height="70" as="geometry" />
        </mxCell>
        <mxCell id="2embDGzhRkxAqKEgTfxS-38" value="manage own orders" style="ellipse;whiteSpace=wrap;html=1;" vertex="1" parent="1">
          <mxGeometry x="-90" y="605" width="140" height="70" as="geometry" />
        </mxCell>
        <mxCell id="2embDGzhRkxAqKEgTfxS-45" style="edgeStyle=orthogonalEdgeStyle;rounded=0;orthogonalLoop=1;jettySize=auto;html=1;exitX=0.5;exitY=0;exitDx=0;exitDy=0;exitPerimeter=0;entryX=0.5;entryY=1;entryDx=0;entryDy=0;" edge="1" parent="1" source="2embDGzhRkxAqKEgTfxS-43" target="2embDGzhRkxAqKEgTfxS-44">
          <mxGeometry relative="1" as="geometry" />
        </mxCell>
        <mxCell id="2embDGzhRkxAqKEgTfxS-47" style="edgeStyle=orthogonalEdgeStyle;rounded=0;orthogonalLoop=1;jettySize=auto;html=1;exitX=1;exitY=0.3333333333333333;exitDx=0;exitDy=0;exitPerimeter=0;entryX=0;entryY=0.5;entryDx=0;entryDy=0;" edge="1" parent="1" source="2embDGzhRkxAqKEgTfxS-43" target="2embDGzhRkxAqKEgTfxS-46">
          <mxGeometry relative="1" as="geometry" />
        </mxCell>
        <mxCell id="2embDGzhRkxAqKEgTfxS-43" value="Admin" style="shape=umlActor;verticalLabelPosition=bottom;verticalAlign=top;html=1;" vertex="1" parent="1">
          <mxGeometry x="510" y="620" width="30" height="60" as="geometry" />
        </mxCell>
        <mxCell id="2embDGzhRkxAqKEgTfxS-44" value="change user roles" style="ellipse;whiteSpace=wrap;html=1;" vertex="1" parent="1">
          <mxGeometry x="455" y="500" width="140" height="70" as="geometry" />
        </mxCell>
        <mxCell id="2embDGzhRkxAqKEgTfxS-46" value="manage all artworks/comments" style="ellipse;whiteSpace=wrap;html=1;" vertex="1" parent="1">
          <mxGeometry x="700" y="605" width="140" height="70" as="geometry" />
        </mxCell>
        <mxCell id="2embDGzhRkxAqKEgTfxS-49" value="manage own comments" style="ellipse;whiteSpace=wrap;html=1;" vertex="1" parent="1">
          <mxGeometry x="450" y="-30" width="140" height="70" as="geometry" />
        </mxCell>
        <mxCell id="2embDGzhRkxAqKEgTfxS-51" value="manage own likes" style="ellipse;whiteSpace=wrap;html=1;" vertex="1" parent="1">
          <mxGeometry x="860" y="205" width="140" height="70" as="geometry" />
        </mxCell>
        <mxCell id="2embDGzhRkxAqKEgTfxS-54" value="Use the search and filter" style="ellipse;whiteSpace=wrap;html=1;" vertex="1" parent="1">
          <mxGeometry x="160" y="120" width="140" height="70" as="geometry" />
        </mxCell>
        <mxCell id="2embDGzhRkxAqKEgTfxS-63" value="manage own conversations" style="ellipse;whiteSpace=wrap;html=1;" vertex="1" parent="1">
          <mxGeometry x="700" y="350" width="140" height="70" as="geometry" />
        </mxCell>
        <mxCell id="2embDGzhRkxAqKEgTfxS-65" value="manage own orders" style="ellipse;whiteSpace=wrap;html=1;" vertex="1" parent="1">
          <mxGeometry x="700" y="120" width="140" height="70" as="geometry" />
        </mxCell>
        <mxCell id="2embDGzhRkxAqKEgTfxS-74" style="edgeStyle=orthogonalEdgeStyle;rounded=0;orthogonalLoop=1;jettySize=auto;html=1;exitX=0;exitY=0.5;exitDx=0;exitDy=0;entryX=1;entryY=0.5;entryDx=0;entryDy=0;" edge="1" parent="1" source="2embDGzhRkxAqKEgTfxS-67" target="2embDGzhRkxAqKEgTfxS-69">
          <mxGeometry relative="1" as="geometry" />
        </mxCell>
        <mxCell id="2embDGzhRkxAqKEgTfxS-67" value="Add artworks" style="ellipse;whiteSpace=wrap;html=1;" vertex="1" parent="1">
          <mxGeometry x="75" y="500" width="140" height="70" as="geometry" />
        </mxCell>
        <mxCell id="2embDGzhRkxAqKEgTfxS-69" value="manage own artworks" style="ellipse;whiteSpace=wrap;html=1;" vertex="1" parent="1">
          <mxGeometry x="-90" y="500" width="140" height="70" as="geometry" />
        </mxCell>
        <mxCell id="2embDGzhRkxAqKEgTfxS-71" value="manage own conversations" style="ellipse;whiteSpace=wrap;html=1;" vertex="1" parent="1">
          <mxGeometry x="230" y="500" width="140" height="70" as="geometry" />
        </mxCell>
        <mxCell id="2embDGzhRkxAqKEgTfxS-75" style="edgeStyle=orthogonalEdgeStyle;rounded=0;orthogonalLoop=1;jettySize=auto;html=1;exitX=1;exitY=0.3333333333333333;exitDx=0;exitDy=0;exitPerimeter=0;entryX=0.5;entryY=1;entryDx=0;entryDy=0;" edge="1" parent="1" source="2embDGzhRkxAqKEgTfxS-79" target="2embDGzhRkxAqKEgTfxS-114">
          <mxGeometry relative="1" as="geometry" />
        </mxCell>
        <mxCell id="2embDGzhRkxAqKEgTfxS-76" style="edgeStyle=orthogonalEdgeStyle;rounded=0;orthogonalLoop=1;jettySize=auto;html=1;exitX=0;exitY=0.3333333333333333;exitDx=0;exitDy=0;exitPerimeter=0;entryX=1;entryY=0.5;entryDx=0;entryDy=0;" edge="1" parent="1" source="2embDGzhRkxAqKEgTfxS-79" target="2embDGzhRkxAqKEgTfxS-82">
          <mxGeometry relative="1" as="geometry" />
        </mxCell>
        <mxCell id="2embDGzhRkxAqKEgTfxS-77" style="edgeStyle=orthogonalEdgeStyle;rounded=0;orthogonalLoop=1;jettySize=auto;html=1;exitX=0;exitY=1;exitDx=0;exitDy=0;exitPerimeter=0;entryX=0.5;entryY=0;entryDx=0;entryDy=0;" edge="1" parent="1" source="2embDGzhRkxAqKEgTfxS-79" target="2embDGzhRkxAqKEgTfxS-80">
          <mxGeometry relative="1" as="geometry" />
        </mxCell>
        <mxCell id="2embDGzhRkxAqKEgTfxS-78" style="edgeStyle=orthogonalEdgeStyle;rounded=0;orthogonalLoop=1;jettySize=auto;html=1;exitX=1;exitY=1;exitDx=0;exitDy=0;exitPerimeter=0;entryX=0.5;entryY=0;entryDx=0;entryDy=0;" edge="1" parent="1" source="2embDGzhRkxAqKEgTfxS-79" target="2embDGzhRkxAqKEgTfxS-81">
          <mxGeometry relative="1" as="geometry" />
        </mxCell>
        <mxCell id="2embDGzhRkxAqKEgTfxS-79" value="Visitor" style="shape=umlActor;verticalLabelPosition=bottom;verticalAlign=top;html=1;" vertex="1" parent="1">
          <mxGeometry x="130" y="205" width="30" height="60" as="geometry" />
        </mxCell>
        <mxCell id="2embDGzhRkxAqKEgTfxS-80" value="Watch artworks" style="ellipse;whiteSpace=wrap;html=1;" vertex="1" parent="1">
          <mxGeometry x="-90" y="350" width="140" height="70" as="geometry" />
        </mxCell>
        <mxCell id="2embDGzhRkxAqKEgTfxS-81" value="Watch artist profile" style="ellipse;whiteSpace=wrap;html=1;" vertex="1" parent="1">
          <mxGeometry x="200" y="340" width="140" height="70" as="geometry" />
        </mxCell>
        <mxCell id="2embDGzhRkxAqKEgTfxS-82" value="Register" style="ellipse;whiteSpace=wrap;html=1;" vertex="1" parent="1">
          <mxGeometry x="-90" y="190" width="140" height="70" as="geometry" />
        </mxCell>
        <mxCell id="2embDGzhRkxAqKEgTfxS-83" style="edgeStyle=orthogonalEdgeStyle;rounded=0;orthogonalLoop=1;jettySize=auto;html=1;exitX=1;exitY=1;exitDx=0;exitDy=0;exitPerimeter=0;" edge="1" parent="1" source="2embDGzhRkxAqKEgTfxS-89" target="2embDGzhRkxAqKEgTfxS-96">
          <mxGeometry relative="1" as="geometry" />
        </mxCell>
        <mxCell id="2embDGzhRkxAqKEgTfxS-84" style="edgeStyle=orthogonalEdgeStyle;rounded=0;orthogonalLoop=1;jettySize=auto;html=1;exitX=0;exitY=0.3333333333333333;exitDx=0;exitDy=0;exitPerimeter=0;entryX=1;entryY=0.5;entryDx=0;entryDy=0;" edge="1" parent="1" source="2embDGzhRkxAqKEgTfxS-89" target="2embDGzhRkxAqKEgTfxS-97">
          <mxGeometry relative="1" as="geometry" />
        </mxCell>
        <mxCell id="2embDGzhRkxAqKEgTfxS-85" style="edgeStyle=orthogonalEdgeStyle;rounded=0;orthogonalLoop=1;jettySize=auto;html=1;exitX=1;exitY=0.3333333333333333;exitDx=0;exitDy=0;exitPerimeter=0;entryX=0;entryY=0.5;entryDx=0;entryDy=0;" edge="1" parent="1" source="2embDGzhRkxAqKEgTfxS-89" target="2embDGzhRkxAqKEgTfxS-94">
          <mxGeometry relative="1" as="geometry" />
        </mxCell>
        <mxCell id="2embDGzhRkxAqKEgTfxS-86" style="edgeStyle=orthogonalEdgeStyle;rounded=0;orthogonalLoop=1;jettySize=auto;html=1;exitX=0.75;exitY=0.1;exitDx=0;exitDy=0;exitPerimeter=0;entryX=0.5;entryY=1;entryDx=0;entryDy=0;" edge="1" parent="1" source="2embDGzhRkxAqKEgTfxS-89" target="2embDGzhRkxAqKEgTfxS-105">
          <mxGeometry relative="1" as="geometry" />
        </mxCell>
        <mxCell id="2embDGzhRkxAqKEgTfxS-87" style="edgeStyle=orthogonalEdgeStyle;rounded=0;orthogonalLoop=1;jettySize=auto;html=1;exitX=0.5;exitY=0;exitDx=0;exitDy=0;exitPerimeter=0;entryX=0.5;entryY=1;entryDx=0;entryDy=0;" edge="1" parent="1" source="2embDGzhRkxAqKEgTfxS-89" target="2embDGzhRkxAqKEgTfxS-92">
          <mxGeometry relative="1" as="geometry" />
        </mxCell>
        <mxCell id="2embDGzhRkxAqKEgTfxS-88" style="edgeStyle=orthogonalEdgeStyle;rounded=0;orthogonalLoop=1;jettySize=auto;html=1;exitX=0;exitY=1;exitDx=0;exitDy=0;exitPerimeter=0;entryX=0.5;entryY=0;entryDx=0;entryDy=0;" edge="1" parent="1" source="2embDGzhRkxAqKEgTfxS-89" target="2embDGzhRkxAqKEgTfxS-90">
          <mxGeometry relative="1" as="geometry" />
        </mxCell>
        <mxCell id="2embDGzhRkxAqKEgTfxS-89" value="User (Logged in)" style="shape=umlActor;verticalLabelPosition=bottom;verticalAlign=top;html=1;" vertex="1" parent="1">
          <mxGeometry x="505" y="220" width="30" height="60" as="geometry" />
        </mxCell>
        <mxCell id="2embDGzhRkxAqKEgTfxS-90" value="Login" style="ellipse;whiteSpace=wrap;html=1;" vertex="1" parent="1">
          <mxGeometry x="370" y="350" width="140" height="70" as="geometry" />
        </mxCell>
        <mxCell id="2embDGzhRkxAqKEgTfxS-91" style="edgeStyle=orthogonalEdgeStyle;rounded=0;orthogonalLoop=1;jettySize=auto;html=1;entryX=0.5;entryY=1;entryDx=0;entryDy=0;" edge="1" parent="1" source="2embDGzhRkxAqKEgTfxS-92" target="2embDGzhRkxAqKEgTfxS-112">
          <mxGeometry relative="1" as="geometry" />
        </mxCell>
        <mxCell id="2embDGzhRkxAqKEgTfxS-92" value="Write comments" style="ellipse;whiteSpace=wrap;html=1;" vertex="1" parent="1">
          <mxGeometry x="450" y="60" width="140" height="60" as="geometry" />
        </mxCell>
        <mxCell id="2embDGzhRkxAqKEgTfxS-93" style="edgeStyle=orthogonalEdgeStyle;rounded=0;orthogonalLoop=1;jettySize=auto;html=1;exitX=1;exitY=0.5;exitDx=0;exitDy=0;entryX=0;entryY=0.5;entryDx=0;entryDy=0;" edge="1" parent="1" source="2embDGzhRkxAqKEgTfxS-94" target="2embDGzhRkxAqKEgTfxS-113">
          <mxGeometry relative="1" as="geometry" />
        </mxCell>
        <mxCell id="2embDGzhRkxAqKEgTfxS-94" value="Like artworks" style="ellipse;whiteSpace=wrap;html=1;" vertex="1" parent="1">
          <mxGeometry x="700" y="205" width="140" height="70" as="geometry" />
        </mxCell>
        <mxCell id="2embDGzhRkxAqKEgTfxS-95" style="edgeStyle=orthogonalEdgeStyle;rounded=0;orthogonalLoop=1;jettySize=auto;html=1;exitX=1;exitY=0.5;exitDx=0;exitDy=0;entryX=0;entryY=0.5;entryDx=0;entryDy=0;" edge="1" parent="1" source="2embDGzhRkxAqKEgTfxS-96" target="2embDGzhRkxAqKEgTfxS-115">
          <mxGeometry relative="1" as="geometry" />
        </mxCell>
        <mxCell id="2embDGzhRkxAqKEgTfxS-96" value="Start a conversation with an artist" style="ellipse;whiteSpace=wrap;html=1;" vertex="1" parent="1">
          <mxGeometry x="535" y="350" width="140" height="70" as="geometry" />
        </mxCell>
        <mxCell id="2embDGzhRkxAqKEgTfxS-97" value="manage personnal informations" style="ellipse;whiteSpace=wrap;html=1;" vertex="1" parent="1">
          <mxGeometry x="340" y="205" width="140" height="70" as="geometry" />
        </mxCell>
        <mxCell id="2embDGzhRkxAqKEgTfxS-98" style="edgeStyle=orthogonalEdgeStyle;rounded=0;orthogonalLoop=1;jettySize=auto;html=1;exitX=1;exitY=0.3333333333333333;exitDx=0;exitDy=0;exitPerimeter=0;entryX=0;entryY=0.5;entryDx=0;entryDy=0;" edge="1" parent="1" source="2embDGzhRkxAqKEgTfxS-101" target="2embDGzhRkxAqKEgTfxS-103">
          <mxGeometry relative="1" as="geometry" />
        </mxCell>
        <mxCell id="2embDGzhRkxAqKEgTfxS-99" style="edgeStyle=orthogonalEdgeStyle;rounded=0;orthogonalLoop=1;jettySize=auto;html=1;exitX=0;exitY=0.3333333333333333;exitDx=0;exitDy=0;exitPerimeter=0;" edge="1" parent="1" source="2embDGzhRkxAqKEgTfxS-101" target="2embDGzhRkxAqKEgTfxS-106">
          <mxGeometry relative="1" as="geometry" />
        </mxCell>
        <mxCell id="2embDGzhRkxAqKEgTfxS-100" style="edgeStyle=orthogonalEdgeStyle;rounded=0;orthogonalLoop=1;jettySize=auto;html=1;exitX=0.5;exitY=0;exitDx=0;exitDy=0;exitPerimeter=0;entryX=0.5;entryY=1;entryDx=0;entryDy=0;" edge="1" parent="1" source="2embDGzhRkxAqKEgTfxS-101" target="2embDGzhRkxAqKEgTfxS-118">
          <mxGeometry relative="1" as="geometry" />
        </mxCell>
        <mxCell id="2embDGzhRkxAqKEgTfxS-101" value="Artist" style="shape=umlActor;verticalLabelPosition=bottom;verticalAlign=top;html=1;" vertex="1" parent="1">
          <mxGeometry x="130" y="620" width="30" height="60" as="geometry" />
        </mxCell>
        <mxCell id="2embDGzhRkxAqKEgTfxS-102" style="edgeStyle=orthogonalEdgeStyle;rounded=0;orthogonalLoop=1;jettySize=auto;html=1;exitX=0.5;exitY=0;exitDx=0;exitDy=0;entryX=0.5;entryY=1;entryDx=0;entryDy=0;" edge="1" parent="1" source="2embDGzhRkxAqKEgTfxS-103" target="2embDGzhRkxAqKEgTfxS-120">
          <mxGeometry relative="1" as="geometry" />
        </mxCell>
        <mxCell id="2embDGzhRkxAqKEgTfxS-103" value="answer conversations" style="ellipse;whiteSpace=wrap;html=1;" vertex="1" parent="1">
          <mxGeometry x="230" y="605" width="140" height="70" as="geometry" />
        </mxCell>
        <mxCell id="2embDGzhRkxAqKEgTfxS-104" style="edgeStyle=orthogonalEdgeStyle;rounded=0;orthogonalLoop=1;jettySize=auto;html=1;exitX=1;exitY=0.5;exitDx=0;exitDy=0;entryX=0;entryY=0.5;entryDx=0;entryDy=0;" edge="1" parent="1" source="2embDGzhRkxAqKEgTfxS-105" target="2embDGzhRkxAqKEgTfxS-116">
          <mxGeometry relative="1" as="geometry" />
        </mxCell>
        <mxCell id="2embDGzhRkxAqKEgTfxS-105" value="Initiate order" style="ellipse;whiteSpace=wrap;html=1;" vertex="1" parent="1">
          <mxGeometry x="540" y="120" width="140" height="70" as="geometry" />
        </mxCell>
        <mxCell id="2embDGzhRkxAqKEgTfxS-106" value="manage own orders" style="ellipse;whiteSpace=wrap;html=1;" vertex="1" parent="1">
          <mxGeometry x="-90" y="605" width="140" height="70" as="geometry" />
        </mxCell>
        <mxCell id="2embDGzhRkxAqKEgTfxS-107" style="edgeStyle=orthogonalEdgeStyle;rounded=0;orthogonalLoop=1;jettySize=auto;html=1;exitX=0.5;exitY=0;exitDx=0;exitDy=0;exitPerimeter=0;entryX=0.5;entryY=1;entryDx=0;entryDy=0;" edge="1" parent="1" source="2embDGzhRkxAqKEgTfxS-109" target="2embDGzhRkxAqKEgTfxS-110">
          <mxGeometry relative="1" as="geometry" />
        </mxCell>
        <mxCell id="2embDGzhRkxAqKEgTfxS-108" style="edgeStyle=orthogonalEdgeStyle;rounded=0;orthogonalLoop=1;jettySize=auto;html=1;exitX=1;exitY=0.3333333333333333;exitDx=0;exitDy=0;exitPerimeter=0;entryX=0;entryY=0.5;entryDx=0;entryDy=0;" edge="1" parent="1" source="2embDGzhRkxAqKEgTfxS-109" target="2embDGzhRkxAqKEgTfxS-111">
          <mxGeometry relative="1" as="geometry" />
        </mxCell>
        <mxCell id="2embDGzhRkxAqKEgTfxS-109" value="Admin" style="shape=umlActor;verticalLabelPosition=bottom;verticalAlign=top;html=1;" vertex="1" parent="1">
          <mxGeometry x="510" y="620" width="30" height="60" as="geometry" />
        </mxCell>
        <mxCell id="2embDGzhRkxAqKEgTfxS-110" value="change user roles" style="ellipse;whiteSpace=wrap;html=1;" vertex="1" parent="1">
          <mxGeometry x="455" y="500" width="140" height="70" as="geometry" />
        </mxCell>
        <mxCell id="2embDGzhRkxAqKEgTfxS-111" value="manage all artworks/comments" style="ellipse;whiteSpace=wrap;html=1;" vertex="1" parent="1">
          <mxGeometry x="700" y="605" width="140" height="70" as="geometry" />
        </mxCell>
        <mxCell id="2embDGzhRkxAqKEgTfxS-112" value="manage own comments" style="ellipse;whiteSpace=wrap;html=1;" vertex="1" parent="1">
          <mxGeometry x="450" y="-30" width="140" height="70" as="geometry" />
        </mxCell>
        <mxCell id="2embDGzhRkxAqKEgTfxS-113" value="manage own likes" style="ellipse;whiteSpace=wrap;html=1;" vertex="1" parent="1">
          <mxGeometry x="860" y="205" width="140" height="70" as="geometry" />
        </mxCell>
        <mxCell id="2embDGzhRkxAqKEgTfxS-114" value="Use the search and filter" style="ellipse;whiteSpace=wrap;html=1;" vertex="1" parent="1">
          <mxGeometry x="160" y="120" width="140" height="70" as="geometry" />
        </mxCell>
        <mxCell id="2embDGzhRkxAqKEgTfxS-115" value="manage own conversations" style="ellipse;whiteSpace=wrap;html=1;" vertex="1" parent="1">
          <mxGeometry x="700" y="350" width="140" height="70" as="geometry" />
        </mxCell>
        <mxCell id="2embDGzhRkxAqKEgTfxS-116" value="manage own orders" style="ellipse;whiteSpace=wrap;html=1;" vertex="1" parent="1">
          <mxGeometry x="700" y="120" width="140" height="70" as="geometry" />
        </mxCell>
        <mxCell id="2embDGzhRkxAqKEgTfxS-117" style="edgeStyle=orthogonalEdgeStyle;rounded=0;orthogonalLoop=1;jettySize=auto;html=1;exitX=0;exitY=0.5;exitDx=0;exitDy=0;entryX=1;entryY=0.5;entryDx=0;entryDy=0;" edge="1" parent="1" source="2embDGzhRkxAqKEgTfxS-118" target="2embDGzhRkxAqKEgTfxS-119">
          <mxGeometry relative="1" as="geometry" />
        </mxCell>
        <mxCell id="2embDGzhRkxAqKEgTfxS-118" value="Add artworks" style="ellipse;whiteSpace=wrap;html=1;" vertex="1" parent="1">
          <mxGeometry x="75" y="500" width="140" height="70" as="geometry" />
        </mxCell>
        <mxCell id="2embDGzhRkxAqKEgTfxS-119" value="manage own artworks" style="ellipse;whiteSpace=wrap;html=1;" vertex="1" parent="1">
          <mxGeometry x="-90" y="500" width="140" height="70" as="geometry" />
        </mxCell>
        <mxCell id="2embDGzhRkxAqKEgTfxS-120" value="manage own conversations" style="ellipse;whiteSpace=wrap;html=1;" vertex="1" parent="1">
          <mxGeometry x="230" y="500" width="140" height="70" as="geometry" />
        </mxCell>
        <mxCell id="2embDGzhRkxAqKEgTfxS-121" value="Artwork" style="swimlane;fontStyle=1;align=center;verticalAlign=top;childLayout=stackLayout;horizontal=1;startSize=26;horizontalStack=0;resizeParent=1;resizeParentMax=0;resizeLast=0;collapsible=1;marginBottom=0;whiteSpace=wrap;html=1;" vertex="1" parent="1">
          <mxGeometry x="1520" y="-1" width="160" height="502" as="geometry" />
        </mxCell>
        <mxCell id="2embDGzhRkxAqKEgTfxS-122" value="+ id" style="text;strokeColor=none;fillColor=none;align=left;verticalAlign=top;spacingLeft=4;spacingRight=4;overflow=hidden;rotatable=0;points=[[0,0.5],[1,0.5]];portConstraint=eastwest;whiteSpace=wrap;html=1;" vertex="1" parent="2embDGzhRkxAqKEgTfxS-121">
          <mxGeometry y="26" width="160" height="26" as="geometry" />
        </mxCell>
        <mxCell id="2embDGzhRkxAqKEgTfxS-128" value="+ title" style="text;strokeColor=none;fillColor=none;align=left;verticalAlign=top;spacingLeft=4;spacingRight=4;overflow=hidden;rotatable=0;points=[[0,0.5],[1,0.5]];portConstraint=eastwest;whiteSpace=wrap;html=1;" vertex="1" parent="2embDGzhRkxAqKEgTfxS-121">
          <mxGeometry y="52" width="160" height="26" as="geometry" />
        </mxCell>
        <mxCell id="2embDGzhRkxAqKEgTfxS-151" value="+ artist_id" style="text;strokeColor=none;fillColor=none;align=left;verticalAlign=top;spacingLeft=4;spacingRight=4;overflow=hidden;rotatable=0;points=[[0,0.5],[1,0.5]];portConstraint=eastwest;whiteSpace=wrap;html=1;" vertex="1" parent="2embDGzhRkxAqKEgTfxS-121">
          <mxGeometry y="78" width="160" height="26" as="geometry" />
        </mxCell>
        <mxCell id="2embDGzhRkxAqKEgTfxS-152" value="+ description" style="text;strokeColor=none;fillColor=none;align=left;verticalAlign=top;spacingLeft=4;spacingRight=4;overflow=hidden;rotatable=0;points=[[0,0.5],[1,0.5]];portConstraint=eastwest;whiteSpace=wrap;html=1;" vertex="1" parent="2embDGzhRkxAqKEgTfxS-121">
          <mxGeometry y="104" width="160" height="26" as="geometry" />
        </mxCell>
        <mxCell id="2embDGzhRkxAqKEgTfxS-153" value="+ keywords" style="text;strokeColor=none;fillColor=none;align=left;verticalAlign=top;spacingLeft=4;spacingRight=4;overflow=hidden;rotatable=0;points=[[0,0.5],[1,0.5]];portConstraint=eastwest;whiteSpace=wrap;html=1;" vertex="1" parent="2embDGzhRkxAqKEgTfxS-121">
          <mxGeometry y="130" width="160" height="26" as="geometry" />
        </mxCell>
        <mxCell id="2embDGzhRkxAqKEgTfxS-154" value="+ created_at" style="text;strokeColor=none;fillColor=none;align=left;verticalAlign=top;spacingLeft=4;spacingRight=4;overflow=hidden;rotatable=0;points=[[0,0.5],[1,0.5]];portConstraint=eastwest;whiteSpace=wrap;html=1;" vertex="1" parent="2embDGzhRkxAqKEgTfxS-121">
          <mxGeometry y="156" width="160" height="26" as="geometry" />
        </mxCell>
        <mxCell id="2embDGzhRkxAqKEgTfxS-155" value="+ updated_at" style="text;strokeColor=none;fillColor=none;align=left;verticalAlign=top;spacingLeft=4;spacingRight=4;overflow=hidden;rotatable=0;points=[[0,0.5],[1,0.5]];portConstraint=eastwest;whiteSpace=wrap;html=1;" vertex="1" parent="2embDGzhRkxAqKEgTfxS-121">
          <mxGeometry y="182" width="160" height="26" as="geometry" />
        </mxCell>
        <mxCell id="2embDGzhRkxAqKEgTfxS-123" value="" style="line;strokeWidth=1;fillColor=none;align=left;verticalAlign=middle;spacingTop=-1;spacingLeft=3;spacingRight=3;rotatable=0;labelPosition=right;points=[];portConstraint=eastwest;strokeColor=inherit;" vertex="1" parent="2embDGzhRkxAqKEgTfxS-121">
          <mxGeometry y="208" width="160" height="8" as="geometry" />
        </mxCell>
        <mxCell id="2embDGzhRkxAqKEgTfxS-124" value="+ setTitle()" style="text;strokeColor=none;fillColor=none;align=left;verticalAlign=top;spacingLeft=4;spacingRight=4;overflow=hidden;rotatable=0;points=[[0,0.5],[1,0.5]];portConstraint=eastwest;whiteSpace=wrap;html=1;" vertex="1" parent="2embDGzhRkxAqKEgTfxS-121">
          <mxGeometry y="216" width="160" height="26" as="geometry" />
        </mxCell>
        <mxCell id="2embDGzhRkxAqKEgTfxS-125" value="+ setDescription()" style="text;strokeColor=none;fillColor=none;align=left;verticalAlign=top;spacingLeft=4;spacingRight=4;overflow=hidden;rotatable=0;points=[[0,0.5],[1,0.5]];portConstraint=eastwest;whiteSpace=wrap;html=1;" vertex="1" parent="2embDGzhRkxAqKEgTfxS-121">
          <mxGeometry y="242" width="160" height="26" as="geometry" />
        </mxCell>
        <mxCell id="2embDGzhRkxAqKEgTfxS-126" value="+ setKeywords()" style="text;strokeColor=none;fillColor=none;align=left;verticalAlign=top;spacingLeft=4;spacingRight=4;overflow=hidden;rotatable=0;points=[[0,0.5],[1,0.5]];portConstraint=eastwest;whiteSpace=wrap;html=1;" vertex="1" parent="2embDGzhRkxAqKEgTfxS-121">
          <mxGeometry y="268" width="160" height="26" as="geometry" />
        </mxCell>
        <mxCell id="2embDGzhRkxAqKEgTfxS-135" value="+ setArtist()" style="text;strokeColor=none;fillColor=none;align=left;verticalAlign=top;spacingLeft=4;spacingRight=4;overflow=hidden;rotatable=0;points=[[0,0.5],[1,0.5]];portConstraint=eastwest;whiteSpace=wrap;html=1;" vertex="1" parent="2embDGzhRkxAqKEgTfxS-121">
          <mxGeometry y="294" width="160" height="26" as="geometry" />
        </mxCell>
        <mxCell id="2embDGzhRkxAqKEgTfxS-127" value="+ onPrePresist()" style="text;strokeColor=none;fillColor=none;align=left;verticalAlign=top;spacingLeft=4;spacingRight=4;overflow=hidden;rotatable=0;points=[[0,0.5],[1,0.5]];portConstraint=eastwest;whiteSpace=wrap;html=1;" vertex="1" parent="2embDGzhRkxAqKEgTfxS-121">
          <mxGeometry y="320" width="160" height="26" as="geometry" />
        </mxCell>
        <mxCell id="2embDGzhRkxAqKEgTfxS-129" value="+ onPreUpdate()" style="text;strokeColor=none;fillColor=none;align=left;verticalAlign=top;spacingLeft=4;spacingRight=4;overflow=hidden;rotatable=0;points=[[0,0.5],[1,0.5]];portConstraint=eastwest;whiteSpace=wrap;html=1;" vertex="1" parent="2embDGzhRkxAqKEgTfxS-121">
          <mxGeometry y="346" width="160" height="26" as="geometry" />
        </mxCell>
        <mxCell id="2embDGzhRkxAqKEgTfxS-130" value="+ addComment()" style="text;strokeColor=none;fillColor=none;align=left;verticalAlign=top;spacingLeft=4;spacingRight=4;overflow=hidden;rotatable=0;points=[[0,0.5],[1,0.5]];portConstraint=eastwest;whiteSpace=wrap;html=1;" vertex="1" parent="2embDGzhRkxAqKEgTfxS-121">
          <mxGeometry y="372" width="160" height="26" as="geometry" />
        </mxCell>
        <mxCell id="2embDGzhRkxAqKEgTfxS-131" value="+ addOrder()" style="text;strokeColor=none;fillColor=none;align=left;verticalAlign=top;spacingLeft=4;spacingRight=4;overflow=hidden;rotatable=0;points=[[0,0.5],[1,0.5]];portConstraint=eastwest;whiteSpace=wrap;html=1;" vertex="1" parent="2embDGzhRkxAqKEgTfxS-121">
          <mxGeometry y="398" width="160" height="26" as="geometry" />
        </mxCell>
        <mxCell id="2embDGzhRkxAqKEgTfxS-132" value="+ addImage()" style="text;strokeColor=none;fillColor=none;align=left;verticalAlign=top;spacingLeft=4;spacingRight=4;overflow=hidden;rotatable=0;points=[[0,0.5],[1,0.5]];portConstraint=eastwest;whiteSpace=wrap;html=1;" vertex="1" parent="2embDGzhRkxAqKEgTfxS-121">
          <mxGeometry y="424" width="160" height="26" as="geometry" />
        </mxCell>
        <mxCell id="2embDGzhRkxAqKEgTfxS-133" value="+ addConversation()" style="text;strokeColor=none;fillColor=none;align=left;verticalAlign=top;spacingLeft=4;spacingRight=4;overflow=hidden;rotatable=0;points=[[0,0.5],[1,0.5]];portConstraint=eastwest;whiteSpace=wrap;html=1;" vertex="1" parent="2embDGzhRkxAqKEgTfxS-121">
          <mxGeometry y="450" width="160" height="26" as="geometry" />
        </mxCell>
        <mxCell id="2embDGzhRkxAqKEgTfxS-134" value="+ addLike()" style="text;strokeColor=none;fillColor=none;align=left;verticalAlign=top;spacingLeft=4;spacingRight=4;overflow=hidden;rotatable=0;points=[[0,0.5],[1,0.5]];portConstraint=eastwest;whiteSpace=wrap;html=1;" vertex="1" parent="2embDGzhRkxAqKEgTfxS-121">
          <mxGeometry y="476" width="160" height="26" as="geometry" />
        </mxCell>
        <mxCell id="2embDGzhRkxAqKEgTfxS-156" value="ArtworkImage" style="swimlane;fontStyle=1;align=center;verticalAlign=top;childLayout=stackLayout;horizontal=1;startSize=26;horizontalStack=0;resizeParent=1;resizeParentMax=0;resizeLast=0;collapsible=1;marginBottom=0;whiteSpace=wrap;html=1;" vertex="1" parent="1">
          <mxGeometry x="1340" width="160" height="346" as="geometry" />
        </mxCell>
        <mxCell id="2embDGzhRkxAqKEgTfxS-157" value="+ id" style="text;strokeColor=none;fillColor=none;align=left;verticalAlign=top;spacingLeft=4;spacingRight=4;overflow=hidden;rotatable=0;points=[[0,0.5],[1,0.5]];portConstraint=eastwest;whiteSpace=wrap;html=1;" vertex="1" parent="2embDGzhRkxAqKEgTfxS-156">
          <mxGeometry y="26" width="160" height="26" as="geometry" />
        </mxCell>
        <mxCell id="2embDGzhRkxAqKEgTfxS-158" value="+ artwork_id" style="text;strokeColor=none;fillColor=none;align=left;verticalAlign=top;spacingLeft=4;spacingRight=4;overflow=hidden;rotatable=0;points=[[0,0.5],[1,0.5]];portConstraint=eastwest;whiteSpace=wrap;html=1;" vertex="1" parent="2embDGzhRkxAqKEgTfxS-156">
          <mxGeometry y="52" width="160" height="26" as="geometry" />
        </mxCell>
        <mxCell id="2embDGzhRkxAqKEgTfxS-159" value="+ image_name" style="text;strokeColor=none;fillColor=none;align=left;verticalAlign=top;spacingLeft=4;spacingRight=4;overflow=hidden;rotatable=0;points=[[0,0.5],[1,0.5]];portConstraint=eastwest;whiteSpace=wrap;html=1;" vertex="1" parent="2embDGzhRkxAqKEgTfxS-156">
          <mxGeometry y="78" width="160" height="26" as="geometry" />
        </mxCell>
        <mxCell id="2embDGzhRkxAqKEgTfxS-163" value="+ image_file" style="text;strokeColor=none;fillColor=none;align=left;verticalAlign=top;spacingLeft=4;spacingRight=4;overflow=hidden;rotatable=0;points=[[0,0.5],[1,0.5]];portConstraint=eastwest;whiteSpace=wrap;html=1;" vertex="1" parent="2embDGzhRkxAqKEgTfxS-156">
          <mxGeometry y="104" width="160" height="26" as="geometry" />
        </mxCell>
        <mxCell id="2embDGzhRkxAqKEgTfxS-160" value="+ image_size" style="text;strokeColor=none;fillColor=none;align=left;verticalAlign=top;spacingLeft=4;spacingRight=4;overflow=hidden;rotatable=0;points=[[0,0.5],[1,0.5]];portConstraint=eastwest;whiteSpace=wrap;html=1;" vertex="1" parent="2embDGzhRkxAqKEgTfxS-156">
          <mxGeometry y="130" width="160" height="26" as="geometry" />
        </mxCell>
        <mxCell id="2embDGzhRkxAqKEgTfxS-161" value="+ created_at" style="text;strokeColor=none;fillColor=none;align=left;verticalAlign=top;spacingLeft=4;spacingRight=4;overflow=hidden;rotatable=0;points=[[0,0.5],[1,0.5]];portConstraint=eastwest;whiteSpace=wrap;html=1;" vertex="1" parent="2embDGzhRkxAqKEgTfxS-156">
          <mxGeometry y="156" width="160" height="26" as="geometry" />
        </mxCell>
        <mxCell id="2embDGzhRkxAqKEgTfxS-162" value="+ legend" style="text;strokeColor=none;fillColor=none;align=left;verticalAlign=top;spacingLeft=4;spacingRight=4;overflow=hidden;rotatable=0;points=[[0,0.5],[1,0.5]];portConstraint=eastwest;whiteSpace=wrap;html=1;" vertex="1" parent="2embDGzhRkxAqKEgTfxS-156">
          <mxGeometry y="182" width="160" height="26" as="geometry" />
        </mxCell>
        <mxCell id="2embDGzhRkxAqKEgTfxS-164" value="" style="line;strokeWidth=1;fillColor=none;align=left;verticalAlign=middle;spacingTop=-1;spacingLeft=3;spacingRight=3;rotatable=0;labelPosition=right;points=[];portConstraint=eastwest;strokeColor=inherit;" vertex="1" parent="2embDGzhRkxAqKEgTfxS-156">
          <mxGeometry y="208" width="160" height="8" as="geometry" />
        </mxCell>
        <mxCell id="2embDGzhRkxAqKEgTfxS-165" value="+ setArtwork()" style="text;strokeColor=none;fillColor=none;align=left;verticalAlign=top;spacingLeft=4;spacingRight=4;overflow=hidden;rotatable=0;points=[[0,0.5],[1,0.5]];portConstraint=eastwest;whiteSpace=wrap;html=1;" vertex="1" parent="2embDGzhRkxAqKEgTfxS-156">
          <mxGeometry y="216" width="160" height="26" as="geometry" />
        </mxCell>
        <mxCell id="2embDGzhRkxAqKEgTfxS-166" value="+ setImagaName()" style="text;strokeColor=none;fillColor=none;align=left;verticalAlign=top;spacingLeft=4;spacingRight=4;overflow=hidden;rotatable=0;points=[[0,0.5],[1,0.5]];portConstraint=eastwest;whiteSpace=wrap;html=1;" vertex="1" parent="2embDGzhRkxAqKEgTfxS-156">
          <mxGeometry y="242" width="160" height="26" as="geometry" />
        </mxCell>
        <mxCell id="2embDGzhRkxAqKEgTfxS-167" value="+ setImageFile()" style="text;strokeColor=none;fillColor=none;align=left;verticalAlign=top;spacingLeft=4;spacingRight=4;overflow=hidden;rotatable=0;points=[[0,0.5],[1,0.5]];portConstraint=eastwest;whiteSpace=wrap;html=1;" vertex="1" parent="2embDGzhRkxAqKEgTfxS-156">
          <mxGeometry y="268" width="160" height="26" as="geometry" />
        </mxCell>
        <mxCell id="2embDGzhRkxAqKEgTfxS-168" value="+ setImageSize()" style="text;strokeColor=none;fillColor=none;align=left;verticalAlign=top;spacingLeft=4;spacingRight=4;overflow=hidden;rotatable=0;points=[[0,0.5],[1,0.5]];portConstraint=eastwest;whiteSpace=wrap;html=1;" vertex="1" parent="2embDGzhRkxAqKEgTfxS-156">
          <mxGeometry y="294" width="160" height="26" as="geometry" />
        </mxCell>
        <mxCell id="2embDGzhRkxAqKEgTfxS-171" value="+ addLegend()" style="text;strokeColor=none;fillColor=none;align=left;verticalAlign=top;spacingLeft=4;spacingRight=4;overflow=hidden;rotatable=0;points=[[0,0.5],[1,0.5]];portConstraint=eastwest;whiteSpace=wrap;html=1;" vertex="1" parent="2embDGzhRkxAqKEgTfxS-156">
          <mxGeometry y="320" width="160" height="26" as="geometry" />
        </mxCell>
        <mxCell id="2embDGzhRkxAqKEgTfxS-176" value="Comment" style="swimlane;fontStyle=1;align=center;verticalAlign=top;childLayout=stackLayout;horizontal=1;startSize=26;horizontalStack=0;resizeParent=1;resizeParentMax=0;resizeLast=0;collapsible=1;marginBottom=0;whiteSpace=wrap;html=1;" vertex="1" parent="1">
          <mxGeometry x="1340" y="362" width="160" height="346" as="geometry" />
        </mxCell>
        <mxCell id="2embDGzhRkxAqKEgTfxS-177" value="+ id" style="text;strokeColor=none;fillColor=none;align=left;verticalAlign=top;spacingLeft=4;spacingRight=4;overflow=hidden;rotatable=0;points=[[0,0.5],[1,0.5]];portConstraint=eastwest;whiteSpace=wrap;html=1;" vertex="1" parent="2embDGzhRkxAqKEgTfxS-176">
          <mxGeometry y="26" width="160" height="26" as="geometry" />
        </mxCell>
        <mxCell id="2embDGzhRkxAqKEgTfxS-178" value="+ artwork_id" style="text;strokeColor=none;fillColor=none;align=left;verticalAlign=top;spacingLeft=4;spacingRight=4;overflow=hidden;rotatable=0;points=[[0,0.5],[1,0.5]];portConstraint=eastwest;whiteSpace=wrap;html=1;" vertex="1" parent="2embDGzhRkxAqKEgTfxS-176">
          <mxGeometry y="52" width="160" height="26" as="geometry" />
        </mxCell>
        <mxCell id="2embDGzhRkxAqKEgTfxS-179" value="+ commenter_id" style="text;strokeColor=none;fillColor=none;align=left;verticalAlign=top;spacingLeft=4;spacingRight=4;overflow=hidden;rotatable=0;points=[[0,0.5],[1,0.5]];portConstraint=eastwest;whiteSpace=wrap;html=1;" vertex="1" parent="2embDGzhRkxAqKEgTfxS-176">
          <mxGeometry y="78" width="160" height="26" as="geometry" />
        </mxCell>
        <mxCell id="2embDGzhRkxAqKEgTfxS-180" value="+ content" style="text;strokeColor=none;fillColor=none;align=left;verticalAlign=top;spacingLeft=4;spacingRight=4;overflow=hidden;rotatable=0;points=[[0,0.5],[1,0.5]];portConstraint=eastwest;whiteSpace=wrap;html=1;" vertex="1" parent="2embDGzhRkxAqKEgTfxS-176">
          <mxGeometry y="104" width="160" height="26" as="geometry" />
        </mxCell>
        <mxCell id="2embDGzhRkxAqKEgTfxS-182" value="+ created_at" style="text;strokeColor=none;fillColor=none;align=left;verticalAlign=top;spacingLeft=4;spacingRight=4;overflow=hidden;rotatable=0;points=[[0,0.5],[1,0.5]];portConstraint=eastwest;whiteSpace=wrap;html=1;" vertex="1" parent="2embDGzhRkxAqKEgTfxS-176">
          <mxGeometry y="130" width="160" height="26" as="geometry" />
        </mxCell>
        <mxCell id="2embDGzhRkxAqKEgTfxS-183" value="+ updated_at" style="text;strokeColor=none;fillColor=none;align=left;verticalAlign=top;spacingLeft=4;spacingRight=4;overflow=hidden;rotatable=0;points=[[0,0.5],[1,0.5]];portConstraint=eastwest;whiteSpace=wrap;html=1;" vertex="1" parent="2embDGzhRkxAqKEgTfxS-176">
          <mxGeometry y="156" width="160" height="26" as="geometry" />
        </mxCell>
        <mxCell id="2embDGzhRkxAqKEgTfxS-184" value="" style="line;strokeWidth=1;fillColor=none;align=left;verticalAlign=middle;spacingTop=-1;spacingLeft=3;spacingRight=3;rotatable=0;labelPosition=right;points=[];portConstraint=eastwest;strokeColor=inherit;" vertex="1" parent="2embDGzhRkxAqKEgTfxS-176">
          <mxGeometry y="182" width="160" height="8" as="geometry" />
        </mxCell>
        <mxCell id="2embDGzhRkxAqKEgTfxS-185" value="+ setArtwork()" style="text;strokeColor=none;fillColor=none;align=left;verticalAlign=top;spacingLeft=4;spacingRight=4;overflow=hidden;rotatable=0;points=[[0,0.5],[1,0.5]];portConstraint=eastwest;whiteSpace=wrap;html=1;" vertex="1" parent="2embDGzhRkxAqKEgTfxS-176">
          <mxGeometry y="190" width="160" height="26" as="geometry" />
        </mxCell>
        <mxCell id="2embDGzhRkxAqKEgTfxS-186" value="+ setUser()" style="text;strokeColor=none;fillColor=none;align=left;verticalAlign=top;spacingLeft=4;spacingRight=4;overflow=hidden;rotatable=0;points=[[0,0.5],[1,0.5]];portConstraint=eastwest;whiteSpace=wrap;html=1;" vertex="1" parent="2embDGzhRkxAqKEgTfxS-176">
          <mxGeometry y="216" width="160" height="26" as="geometry" />
        </mxCell>
        <mxCell id="2embDGzhRkxAqKEgTfxS-187" value="+ setContent()" style="text;strokeColor=none;fillColor=none;align=left;verticalAlign=top;spacingLeft=4;spacingRight=4;overflow=hidden;rotatable=0;points=[[0,0.5],[1,0.5]];portConstraint=eastwest;whiteSpace=wrap;html=1;" vertex="1" parent="2embDGzhRkxAqKEgTfxS-176">
          <mxGeometry y="242" width="160" height="26" as="geometry" />
        </mxCell>
        <mxCell id="2embDGzhRkxAqKEgTfxS-188" value="+ setImageSize()" style="text;strokeColor=none;fillColor=none;align=left;verticalAlign=top;spacingLeft=4;spacingRight=4;overflow=hidden;rotatable=0;points=[[0,0.5],[1,0.5]];portConstraint=eastwest;whiteSpace=wrap;html=1;" vertex="1" parent="2embDGzhRkxAqKEgTfxS-176">
          <mxGeometry y="268" width="160" height="26" as="geometry" />
        </mxCell>
        <mxCell id="2embDGzhRkxAqKEgTfxS-190" value="+ onPreUpdate()" style="text;strokeColor=none;fillColor=none;align=left;verticalAlign=top;spacingLeft=4;spacingRight=4;overflow=hidden;rotatable=0;points=[[0,0.5],[1,0.5]];portConstraint=eastwest;whiteSpace=wrap;html=1;" vertex="1" parent="2embDGzhRkxAqKEgTfxS-176">
          <mxGeometry y="294" width="160" height="26" as="geometry" />
        </mxCell>
        <mxCell id="2embDGzhRkxAqKEgTfxS-191" value="+ onPrePresist()" style="text;strokeColor=none;fillColor=none;align=left;verticalAlign=top;spacingLeft=4;spacingRight=4;overflow=hidden;rotatable=0;points=[[0,0.5],[1,0.5]];portConstraint=eastwest;whiteSpace=wrap;html=1;" vertex="1" parent="2embDGzhRkxAqKEgTfxS-176">
          <mxGeometry y="320" width="160" height="26" as="geometry" />
        </mxCell>
        <mxCell id="2embDGzhRkxAqKEgTfxS-192" value="Conversation" style="swimlane;fontStyle=1;align=center;verticalAlign=top;childLayout=stackLayout;horizontal=1;startSize=26;horizontalStack=0;resizeParent=1;resizeParentMax=0;resizeLast=0;collapsible=1;marginBottom=0;whiteSpace=wrap;html=1;" vertex="1" parent="1">
          <mxGeometry x="1880" width="160" height="580" as="geometry" />
        </mxCell>
        <mxCell id="2embDGzhRkxAqKEgTfxS-193" value="+ id" style="text;strokeColor=none;fillColor=none;align=left;verticalAlign=top;spacingLeft=4;spacingRight=4;overflow=hidden;rotatable=0;points=[[0,0.5],[1,0.5]];portConstraint=eastwest;whiteSpace=wrap;html=1;" vertex="1" parent="2embDGzhRkxAqKEgTfxS-192">
          <mxGeometry y="26" width="160" height="26" as="geometry" />
        </mxCell>
        <mxCell id="2embDGzhRkxAqKEgTfxS-194" value="+ artwork_id" style="text;strokeColor=none;fillColor=none;align=left;verticalAlign=top;spacingLeft=4;spacingRight=4;overflow=hidden;rotatable=0;points=[[0,0.5],[1,0.5]];portConstraint=eastwest;whiteSpace=wrap;html=1;" vertex="1" parent="2embDGzhRkxAqKEgTfxS-192">
          <mxGeometry y="52" width="160" height="26" as="geometry" />
        </mxCell>
        <mxCell id="2embDGzhRkxAqKEgTfxS-196" value="+ order_id" style="text;strokeColor=none;fillColor=none;align=left;verticalAlign=top;spacingLeft=4;spacingRight=4;overflow=hidden;rotatable=0;points=[[0,0.5],[1,0.5]];portConstraint=eastwest;whiteSpace=wrap;html=1;" vertex="1" parent="2embDGzhRkxAqKEgTfxS-192">
          <mxGeometry y="78" width="160" height="26" as="geometry" />
        </mxCell>
        <mxCell id="2embDGzhRkxAqKEgTfxS-195" value="+ artist_id" style="text;strokeColor=none;fillColor=none;align=left;verticalAlign=top;spacingLeft=4;spacingRight=4;overflow=hidden;rotatable=0;points=[[0,0.5],[1,0.5]];portConstraint=eastwest;whiteSpace=wrap;html=1;" vertex="1" parent="2embDGzhRkxAqKEgTfxS-192">
          <mxGeometry y="104" width="160" height="26" as="geometry" />
        </mxCell>
        <mxCell id="2embDGzhRkxAqKEgTfxS-197" value="+ client_id" style="text;strokeColor=none;fillColor=none;align=left;verticalAlign=top;spacingLeft=4;spacingRight=4;overflow=hidden;rotatable=0;points=[[0,0.5],[1,0.5]];portConstraint=eastwest;whiteSpace=wrap;html=1;" vertex="1" parent="2embDGzhRkxAqKEgTfxS-192">
          <mxGeometry y="130" width="160" height="26" as="geometry" />
        </mxCell>
        <mxCell id="2embDGzhRkxAqKEgTfxS-198" value="+ created_at" style="text;strokeColor=none;fillColor=none;align=left;verticalAlign=top;spacingLeft=4;spacingRight=4;overflow=hidden;rotatable=0;points=[[0,0.5],[1,0.5]];portConstraint=eastwest;whiteSpace=wrap;html=1;" vertex="1" parent="2embDGzhRkxAqKEgTfxS-192">
          <mxGeometry y="156" width="160" height="26" as="geometry" />
        </mxCell>
        <mxCell id="2embDGzhRkxAqKEgTfxS-199" value="+ updated_at" style="text;strokeColor=none;fillColor=none;align=left;verticalAlign=top;spacingLeft=4;spacingRight=4;overflow=hidden;rotatable=0;points=[[0,0.5],[1,0.5]];portConstraint=eastwest;whiteSpace=wrap;html=1;" vertex="1" parent="2embDGzhRkxAqKEgTfxS-192">
          <mxGeometry y="182" width="160" height="26" as="geometry" />
        </mxCell>
        <mxCell id="2embDGzhRkxAqKEgTfxS-212" value="+ is_deleted_by_artist" style="text;strokeColor=none;fillColor=none;align=left;verticalAlign=top;spacingLeft=4;spacingRight=4;overflow=hidden;rotatable=0;points=[[0,0.5],[1,0.5]];portConstraint=eastwest;whiteSpace=wrap;html=1;" vertex="1" parent="2embDGzhRkxAqKEgTfxS-192">
          <mxGeometry y="208" width="160" height="26" as="geometry" />
        </mxCell>
        <mxCell id="2embDGzhRkxAqKEgTfxS-213" value="+ is_deleted_by_client" style="text;strokeColor=none;fillColor=none;align=left;verticalAlign=top;spacingLeft=4;spacingRight=4;overflow=hidden;rotatable=0;points=[[0,0.5],[1,0.5]];portConstraint=eastwest;whiteSpace=wrap;html=1;" vertex="1" parent="2embDGzhRkxAqKEgTfxS-192">
          <mxGeometry y="234" width="160" height="26" as="geometry" />
        </mxCell>
        <mxCell id="2embDGzhRkxAqKEgTfxS-200" value="" style="line;strokeWidth=1;fillColor=none;align=left;verticalAlign=middle;spacingTop=-1;spacingLeft=3;spacingRight=3;rotatable=0;labelPosition=right;points=[];portConstraint=eastwest;strokeColor=inherit;" vertex="1" parent="2embDGzhRkxAqKEgTfxS-192">
          <mxGeometry y="260" width="160" height="8" as="geometry" />
        </mxCell>
        <mxCell id="2embDGzhRkxAqKEgTfxS-201" value="+ setArtwork()" style="text;strokeColor=none;fillColor=none;align=left;verticalAlign=top;spacingLeft=4;spacingRight=4;overflow=hidden;rotatable=0;points=[[0,0.5],[1,0.5]];portConstraint=eastwest;whiteSpace=wrap;html=1;" vertex="1" parent="2embDGzhRkxAqKEgTfxS-192">
          <mxGeometry y="268" width="160" height="26" as="geometry" />
        </mxCell>
        <mxCell id="2embDGzhRkxAqKEgTfxS-202" value="+ setOrder()" style="text;strokeColor=none;fillColor=none;align=left;verticalAlign=top;spacingLeft=4;spacingRight=4;overflow=hidden;rotatable=0;points=[[0,0.5],[1,0.5]];portConstraint=eastwest;whiteSpace=wrap;html=1;" vertex="1" parent="2embDGzhRkxAqKEgTfxS-192">
          <mxGeometry y="294" width="160" height="26" as="geometry" />
        </mxCell>
        <mxCell id="2embDGzhRkxAqKEgTfxS-203" value="+ setClient()" style="text;strokeColor=none;fillColor=none;align=left;verticalAlign=top;spacingLeft=4;spacingRight=4;overflow=hidden;rotatable=0;points=[[0,0.5],[1,0.5]];portConstraint=eastwest;whiteSpace=wrap;html=1;" vertex="1" parent="2embDGzhRkxAqKEgTfxS-192">
          <mxGeometry y="320" width="160" height="26" as="geometry" />
        </mxCell>
        <mxCell id="2embDGzhRkxAqKEgTfxS-204" value="+ setArtist()" style="text;strokeColor=none;fillColor=none;align=left;verticalAlign=top;spacingLeft=4;spacingRight=4;overflow=hidden;rotatable=0;points=[[0,0.5],[1,0.5]];portConstraint=eastwest;whiteSpace=wrap;html=1;" vertex="1" parent="2embDGzhRkxAqKEgTfxS-192">
          <mxGeometry y="346" width="160" height="26" as="geometry" />
        </mxCell>
        <mxCell id="2embDGzhRkxAqKEgTfxS-205" value="+ onPrePresist()" style="text;strokeColor=none;fillColor=none;align=left;verticalAlign=top;spacingLeft=4;spacingRight=4;overflow=hidden;rotatable=0;points=[[0,0.5],[1,0.5]];portConstraint=eastwest;whiteSpace=wrap;html=1;" vertex="1" parent="2embDGzhRkxAqKEgTfxS-192">
          <mxGeometry y="372" width="160" height="26" as="geometry" />
        </mxCell>
        <mxCell id="2embDGzhRkxAqKEgTfxS-206" value="+ onPreUpdate()" style="text;strokeColor=none;fillColor=none;align=left;verticalAlign=top;spacingLeft=4;spacingRight=4;overflow=hidden;rotatable=0;points=[[0,0.5],[1,0.5]];portConstraint=eastwest;whiteSpace=wrap;html=1;" vertex="1" parent="2embDGzhRkxAqKEgTfxS-192">
          <mxGeometry y="398" width="160" height="26" as="geometry" />
        </mxCell>
        <mxCell id="2embDGzhRkxAqKEgTfxS-207" value="+ addMessage()" style="text;strokeColor=none;fillColor=none;align=left;verticalAlign=top;spacingLeft=4;spacingRight=4;overflow=hidden;rotatable=0;points=[[0,0.5],[1,0.5]];portConstraint=eastwest;whiteSpace=wrap;html=1;" vertex="1" parent="2embDGzhRkxAqKEgTfxS-192">
          <mxGeometry y="424" width="160" height="26" as="geometry" />
        </mxCell>
        <mxCell id="2embDGzhRkxAqKEgTfxS-208" value="+ isParticipant()" style="text;strokeColor=none;fillColor=none;align=left;verticalAlign=top;spacingLeft=4;spacingRight=4;overflow=hidden;rotatable=0;points=[[0,0.5],[1,0.5]];portConstraint=eastwest;whiteSpace=wrap;html=1;" vertex="1" parent="2embDGzhRkxAqKEgTfxS-192">
          <mxGeometry y="450" width="160" height="26" as="geometry" />
        </mxCell>
        <mxCell id="2embDGzhRkxAqKEgTfxS-209" value="+ isDeletedByBoth()" style="text;strokeColor=none;fillColor=none;align=left;verticalAlign=top;spacingLeft=4;spacingRight=4;overflow=hidden;rotatable=0;points=[[0,0.5],[1,0.5]];portConstraint=eastwest;whiteSpace=wrap;html=1;" vertex="1" parent="2embDGzhRkxAqKEgTfxS-192">
          <mxGeometry y="476" width="160" height="26" as="geometry" />
        </mxCell>
        <mxCell id="2embDGzhRkxAqKEgTfxS-210" value="+ getOtherParticipant()" style="text;strokeColor=none;fillColor=none;align=left;verticalAlign=top;spacingLeft=4;spacingRight=4;overflow=hidden;rotatable=0;points=[[0,0.5],[1,0.5]];portConstraint=eastwest;whiteSpace=wrap;html=1;" vertex="1" parent="2embDGzhRkxAqKEgTfxS-192">
          <mxGeometry y="502" width="160" height="26" as="geometry" />
        </mxCell>
        <mxCell id="2embDGzhRkxAqKEgTfxS-211" value="+ setIsDeletedByArtist()" style="text;strokeColor=none;fillColor=none;align=left;verticalAlign=top;spacingLeft=4;spacingRight=4;overflow=hidden;rotatable=0;points=[[0,0.5],[1,0.5]];portConstraint=eastwest;whiteSpace=wrap;html=1;" vertex="1" parent="2embDGzhRkxAqKEgTfxS-192">
          <mxGeometry y="528" width="160" height="26" as="geometry" />
        </mxCell>
        <mxCell id="2embDGzhRkxAqKEgTfxS-214" value="+ setIsDeletedByClient()" style="text;strokeColor=none;fillColor=none;align=left;verticalAlign=top;spacingLeft=4;spacingRight=4;overflow=hidden;rotatable=0;points=[[0,0.5],[1,0.5]];portConstraint=eastwest;whiteSpace=wrap;html=1;" vertex="1" parent="2embDGzhRkxAqKEgTfxS-192">
          <mxGeometry y="554" width="160" height="26" as="geometry" />
        </mxCell>
        <mxCell id="2embDGzhRkxAqKEgTfxS-215" value="Like" style="swimlane;fontStyle=1;align=center;verticalAlign=top;childLayout=stackLayout;horizontal=1;startSize=26;horizontalStack=0;resizeParent=1;resizeParentMax=0;resizeLast=0;collapsible=1;marginBottom=0;whiteSpace=wrap;html=1;" vertex="1" parent="1">
          <mxGeometry x="1520" y="520" width="160" height="216" as="geometry" />
        </mxCell>
        <mxCell id="2embDGzhRkxAqKEgTfxS-216" value="+ id" style="text;strokeColor=none;fillColor=none;align=left;verticalAlign=top;spacingLeft=4;spacingRight=4;overflow=hidden;rotatable=0;points=[[0,0.5],[1,0.5]];portConstraint=eastwest;whiteSpace=wrap;html=1;" vertex="1" parent="2embDGzhRkxAqKEgTfxS-215">
          <mxGeometry y="26" width="160" height="26" as="geometry" />
        </mxCell>
        <mxCell id="2embDGzhRkxAqKEgTfxS-217" value="+ artwork_id" style="text;strokeColor=none;fillColor=none;align=left;verticalAlign=top;spacingLeft=4;spacingRight=4;overflow=hidden;rotatable=0;points=[[0,0.5],[1,0.5]];portConstraint=eastwest;whiteSpace=wrap;html=1;" vertex="1" parent="2embDGzhRkxAqKEgTfxS-215">
          <mxGeometry y="52" width="160" height="26" as="geometry" />
        </mxCell>
        <mxCell id="2embDGzhRkxAqKEgTfxS-218" value="+ client_id" style="text;strokeColor=none;fillColor=none;align=left;verticalAlign=top;spacingLeft=4;spacingRight=4;overflow=hidden;rotatable=0;points=[[0,0.5],[1,0.5]];portConstraint=eastwest;whiteSpace=wrap;html=1;" vertex="1" parent="2embDGzhRkxAqKEgTfxS-215">
          <mxGeometry y="78" width="160" height="26" as="geometry" />
        </mxCell>
        <mxCell id="2embDGzhRkxAqKEgTfxS-221" value="+ created_at" style="text;strokeColor=none;fillColor=none;align=left;verticalAlign=top;spacingLeft=4;spacingRight=4;overflow=hidden;rotatable=0;points=[[0,0.5],[1,0.5]];portConstraint=eastwest;whiteSpace=wrap;html=1;" vertex="1" parent="2embDGzhRkxAqKEgTfxS-215">
          <mxGeometry y="104" width="160" height="26" as="geometry" />
        </mxCell>
        <mxCell id="2embDGzhRkxAqKEgTfxS-223" value="" style="line;strokeWidth=1;fillColor=none;align=left;verticalAlign=middle;spacingTop=-1;spacingLeft=3;spacingRight=3;rotatable=0;labelPosition=right;points=[];portConstraint=eastwest;strokeColor=inherit;" vertex="1" parent="2embDGzhRkxAqKEgTfxS-215">
          <mxGeometry y="130" width="160" height="8" as="geometry" />
        </mxCell>
        <mxCell id="2embDGzhRkxAqKEgTfxS-224" value="+ setArtwork()" style="text;strokeColor=none;fillColor=none;align=left;verticalAlign=top;spacingLeft=4;spacingRight=4;overflow=hidden;rotatable=0;points=[[0,0.5],[1,0.5]];portConstraint=eastwest;whiteSpace=wrap;html=1;" vertex="1" parent="2embDGzhRkxAqKEgTfxS-215">
          <mxGeometry y="138" width="160" height="26" as="geometry" />
        </mxCell>
        <mxCell id="2embDGzhRkxAqKEgTfxS-227" value="+ setClient()" style="text;strokeColor=none;fillColor=none;align=left;verticalAlign=top;spacingLeft=4;spacingRight=4;overflow=hidden;rotatable=0;points=[[0,0.5],[1,0.5]];portConstraint=eastwest;whiteSpace=wrap;html=1;" vertex="1" parent="2embDGzhRkxAqKEgTfxS-215">
          <mxGeometry y="164" width="160" height="26" as="geometry" />
        </mxCell>
        <mxCell id="2embDGzhRkxAqKEgTfxS-229" value="+ onPrePresist()" style="text;strokeColor=none;fillColor=none;align=left;verticalAlign=top;spacingLeft=4;spacingRight=4;overflow=hidden;rotatable=0;points=[[0,0.5],[1,0.5]];portConstraint=eastwest;whiteSpace=wrap;html=1;" vertex="1" parent="2embDGzhRkxAqKEgTfxS-215">
          <mxGeometry y="190" width="160" height="26" as="geometry" />
        </mxCell>
        <mxCell id="2embDGzhRkxAqKEgTfxS-230" value="Message" style="swimlane;fontStyle=1;align=center;verticalAlign=top;childLayout=stackLayout;horizontal=1;startSize=26;horizontalStack=0;resizeParent=1;resizeParentMax=0;resizeLast=0;collapsible=1;marginBottom=0;whiteSpace=wrap;html=1;" vertex="1" parent="1">
          <mxGeometry x="2060" width="160" height="268" as="geometry" />
        </mxCell>
        <mxCell id="2embDGzhRkxAqKEgTfxS-231" value="+ id" style="text;strokeColor=none;fillColor=none;align=left;verticalAlign=top;spacingLeft=4;spacingRight=4;overflow=hidden;rotatable=0;points=[[0,0.5],[1,0.5]];portConstraint=eastwest;whiteSpace=wrap;html=1;" vertex="1" parent="2embDGzhRkxAqKEgTfxS-230">
          <mxGeometry y="26" width="160" height="26" as="geometry" />
        </mxCell>
        <mxCell id="2embDGzhRkxAqKEgTfxS-232" value="+ sender_id" style="text;strokeColor=none;fillColor=none;align=left;verticalAlign=top;spacingLeft=4;spacingRight=4;overflow=hidden;rotatable=0;points=[[0,0.5],[1,0.5]];portConstraint=eastwest;whiteSpace=wrap;html=1;" vertex="1" parent="2embDGzhRkxAqKEgTfxS-230">
          <mxGeometry y="52" width="160" height="26" as="geometry" />
        </mxCell>
        <mxCell id="2embDGzhRkxAqKEgTfxS-233" value="+ conversation_id" style="text;strokeColor=none;fillColor=none;align=left;verticalAlign=top;spacingLeft=4;spacingRight=4;overflow=hidden;rotatable=0;points=[[0,0.5],[1,0.5]];portConstraint=eastwest;whiteSpace=wrap;html=1;" vertex="1" parent="2embDGzhRkxAqKEgTfxS-230">
          <mxGeometry y="78" width="160" height="26" as="geometry" />
        </mxCell>
        <mxCell id="2embDGzhRkxAqKEgTfxS-239" value="+ content" style="text;strokeColor=none;fillColor=none;align=left;verticalAlign=top;spacingLeft=4;spacingRight=4;overflow=hidden;rotatable=0;points=[[0,0.5],[1,0.5]];portConstraint=eastwest;whiteSpace=wrap;html=1;" vertex="1" parent="2embDGzhRkxAqKEgTfxS-230">
          <mxGeometry y="104" width="160" height="26" as="geometry" />
        </mxCell>
        <mxCell id="2embDGzhRkxAqKEgTfxS-234" value="+ created_at" style="text;strokeColor=none;fillColor=none;align=left;verticalAlign=top;spacingLeft=4;spacingRight=4;overflow=hidden;rotatable=0;points=[[0,0.5],[1,0.5]];portConstraint=eastwest;whiteSpace=wrap;html=1;" vertex="1" parent="2embDGzhRkxAqKEgTfxS-230">
          <mxGeometry y="130" width="160" height="26" as="geometry" />
        </mxCell>
        <mxCell id="2embDGzhRkxAqKEgTfxS-235" value="" style="line;strokeWidth=1;fillColor=none;align=left;verticalAlign=middle;spacingTop=-1;spacingLeft=3;spacingRight=3;rotatable=0;labelPosition=right;points=[];portConstraint=eastwest;strokeColor=inherit;" vertex="1" parent="2embDGzhRkxAqKEgTfxS-230">
          <mxGeometry y="156" width="160" height="8" as="geometry" />
        </mxCell>
        <mxCell id="2embDGzhRkxAqKEgTfxS-236" value="+ setConversation()" style="text;strokeColor=none;fillColor=none;align=left;verticalAlign=top;spacingLeft=4;spacingRight=4;overflow=hidden;rotatable=0;points=[[0,0.5],[1,0.5]];portConstraint=eastwest;whiteSpace=wrap;html=1;" vertex="1" parent="2embDGzhRkxAqKEgTfxS-230">
          <mxGeometry y="164" width="160" height="26" as="geometry" />
        </mxCell>
        <mxCell id="2embDGzhRkxAqKEgTfxS-237" value="+ setSender()" style="text;strokeColor=none;fillColor=none;align=left;verticalAlign=top;spacingLeft=4;spacingRight=4;overflow=hidden;rotatable=0;points=[[0,0.5],[1,0.5]];portConstraint=eastwest;whiteSpace=wrap;html=1;" vertex="1" parent="2embDGzhRkxAqKEgTfxS-230">
          <mxGeometry y="190" width="160" height="26" as="geometry" />
        </mxCell>
        <mxCell id="2embDGzhRkxAqKEgTfxS-240" value="+ setContent()" style="text;strokeColor=none;fillColor=none;align=left;verticalAlign=top;spacingLeft=4;spacingRight=4;overflow=hidden;rotatable=0;points=[[0,0.5],[1,0.5]];portConstraint=eastwest;whiteSpace=wrap;html=1;" vertex="1" parent="2embDGzhRkxAqKEgTfxS-230">
          <mxGeometry y="216" width="160" height="26" as="geometry" />
        </mxCell>
        <mxCell id="2embDGzhRkxAqKEgTfxS-238" value="+ onPrePresist()" style="text;strokeColor=none;fillColor=none;align=left;verticalAlign=top;spacingLeft=4;spacingRight=4;overflow=hidden;rotatable=0;points=[[0,0.5],[1,0.5]];portConstraint=eastwest;whiteSpace=wrap;html=1;" vertex="1" parent="2embDGzhRkxAqKEgTfxS-230">
          <mxGeometry y="242" width="160" height="26" as="geometry" />
        </mxCell>
        <mxCell id="2embDGzhRkxAqKEgTfxS-241" value="Order" style="swimlane;fontStyle=1;align=center;verticalAlign=top;childLayout=stackLayout;horizontal=1;startSize=26;horizontalStack=0;resizeParent=1;resizeParentMax=0;resizeLast=0;collapsible=1;marginBottom=0;whiteSpace=wrap;html=1;" vertex="1" parent="1">
          <mxGeometry x="2060" y="286" width="160" height="372" as="geometry" />
        </mxCell>
        <mxCell id="2embDGzhRkxAqKEgTfxS-242" value="+ id" style="text;strokeColor=none;fillColor=none;align=left;verticalAlign=top;spacingLeft=4;spacingRight=4;overflow=hidden;rotatable=0;points=[[0,0.5],[1,0.5]];portConstraint=eastwest;whiteSpace=wrap;html=1;" vertex="1" parent="2embDGzhRkxAqKEgTfxS-241">
          <mxGeometry y="26" width="160" height="26" as="geometry" />
        </mxCell>
        <mxCell id="2embDGzhRkxAqKEgTfxS-243" value="+ artwork_id" style="text;strokeColor=none;fillColor=none;align=left;verticalAlign=top;spacingLeft=4;spacingRight=4;overflow=hidden;rotatable=0;points=[[0,0.5],[1,0.5]];portConstraint=eastwest;whiteSpace=wrap;html=1;" vertex="1" parent="2embDGzhRkxAqKEgTfxS-241">
          <mxGeometry y="52" width="160" height="26" as="geometry" />
        </mxCell>
        <mxCell id="2embDGzhRkxAqKEgTfxS-245" value="+ artist_id" style="text;strokeColor=none;fillColor=none;align=left;verticalAlign=top;spacingLeft=4;spacingRight=4;overflow=hidden;rotatable=0;points=[[0,0.5],[1,0.5]];portConstraint=eastwest;whiteSpace=wrap;html=1;" vertex="1" parent="2embDGzhRkxAqKEgTfxS-241">
          <mxGeometry y="78" width="160" height="26" as="geometry" />
        </mxCell>
        <mxCell id="2embDGzhRkxAqKEgTfxS-246" value="+ client_id" style="text;strokeColor=none;fillColor=none;align=left;verticalAlign=top;spacingLeft=4;spacingRight=4;overflow=hidden;rotatable=0;points=[[0,0.5],[1,0.5]];portConstraint=eastwest;whiteSpace=wrap;html=1;" vertex="1" parent="2embDGzhRkxAqKEgTfxS-241">
          <mxGeometry y="104" width="160" height="26" as="geometry" />
        </mxCell>
        <mxCell id="2embDGzhRkxAqKEgTfxS-249" value="+ status" style="text;strokeColor=none;fillColor=none;align=left;verticalAlign=top;spacingLeft=4;spacingRight=4;overflow=hidden;rotatable=0;points=[[0,0.5],[1,0.5]];portConstraint=eastwest;whiteSpace=wrap;html=1;" vertex="1" parent="2embDGzhRkxAqKEgTfxS-241">
          <mxGeometry y="130" width="160" height="26" as="geometry" />
        </mxCell>
        <mxCell id="2embDGzhRkxAqKEgTfxS-247" value="+ created_at" style="text;strokeColor=none;fillColor=none;align=left;verticalAlign=top;spacingLeft=4;spacingRight=4;overflow=hidden;rotatable=0;points=[[0,0.5],[1,0.5]];portConstraint=eastwest;whiteSpace=wrap;html=1;" vertex="1" parent="2embDGzhRkxAqKEgTfxS-241">
          <mxGeometry y="156" width="160" height="26" as="geometry" />
        </mxCell>
        <mxCell id="2embDGzhRkxAqKEgTfxS-248" value="+ updated_at" style="text;strokeColor=none;fillColor=none;align=left;verticalAlign=top;spacingLeft=4;spacingRight=4;overflow=hidden;rotatable=0;points=[[0,0.5],[1,0.5]];portConstraint=eastwest;whiteSpace=wrap;html=1;" vertex="1" parent="2embDGzhRkxAqKEgTfxS-241">
          <mxGeometry y="182" width="160" height="26" as="geometry" />
        </mxCell>
        <mxCell id="2embDGzhRkxAqKEgTfxS-251" value="" style="line;strokeWidth=1;fillColor=none;align=left;verticalAlign=middle;spacingTop=-1;spacingLeft=3;spacingRight=3;rotatable=0;labelPosition=right;points=[];portConstraint=eastwest;strokeColor=inherit;" vertex="1" parent="2embDGzhRkxAqKEgTfxS-241">
          <mxGeometry y="208" width="160" height="8" as="geometry" />
        </mxCell>
        <mxCell id="2embDGzhRkxAqKEgTfxS-252" value="+ setArtwork()" style="text;strokeColor=none;fillColor=none;align=left;verticalAlign=top;spacingLeft=4;spacingRight=4;overflow=hidden;rotatable=0;points=[[0,0.5],[1,0.5]];portConstraint=eastwest;whiteSpace=wrap;html=1;" vertex="1" parent="2embDGzhRkxAqKEgTfxS-241">
          <mxGeometry y="216" width="160" height="26" as="geometry" />
        </mxCell>
        <mxCell id="2embDGzhRkxAqKEgTfxS-254" value="+ setClient()" style="text;strokeColor=none;fillColor=none;align=left;verticalAlign=top;spacingLeft=4;spacingRight=4;overflow=hidden;rotatable=0;points=[[0,0.5],[1,0.5]];portConstraint=eastwest;whiteSpace=wrap;html=1;" vertex="1" parent="2embDGzhRkxAqKEgTfxS-241">
          <mxGeometry y="242" width="160" height="26" as="geometry" />
        </mxCell>
        <mxCell id="2embDGzhRkxAqKEgTfxS-255" value="+ setArtist()" style="text;strokeColor=none;fillColor=none;align=left;verticalAlign=top;spacingLeft=4;spacingRight=4;overflow=hidden;rotatable=0;points=[[0,0.5],[1,0.5]];portConstraint=eastwest;whiteSpace=wrap;html=1;" vertex="1" parent="2embDGzhRkxAqKEgTfxS-241">
          <mxGeometry y="268" width="160" height="26" as="geometry" />
        </mxCell>
        <mxCell id="2embDGzhRkxAqKEgTfxS-258" value="+ setConversation()" style="text;strokeColor=none;fillColor=none;align=left;verticalAlign=top;spacingLeft=4;spacingRight=4;overflow=hidden;rotatable=0;points=[[0,0.5],[1,0.5]];portConstraint=eastwest;whiteSpace=wrap;html=1;" vertex="1" parent="2embDGzhRkxAqKEgTfxS-241">
          <mxGeometry y="294" width="160" height="26" as="geometry" />
        </mxCell>
        <mxCell id="2embDGzhRkxAqKEgTfxS-256" value="+ onPrePresist()" style="text;strokeColor=none;fillColor=none;align=left;verticalAlign=top;spacingLeft=4;spacingRight=4;overflow=hidden;rotatable=0;points=[[0,0.5],[1,0.5]];portConstraint=eastwest;whiteSpace=wrap;html=1;" vertex="1" parent="2embDGzhRkxAqKEgTfxS-241">
          <mxGeometry y="320" width="160" height="26" as="geometry" />
        </mxCell>
        <mxCell id="2embDGzhRkxAqKEgTfxS-257" value="+ onPreUpdate()" style="text;strokeColor=none;fillColor=none;align=left;verticalAlign=top;spacingLeft=4;spacingRight=4;overflow=hidden;rotatable=0;points=[[0,0.5],[1,0.5]];portConstraint=eastwest;whiteSpace=wrap;html=1;" vertex="1" parent="2embDGzhRkxAqKEgTfxS-241">
          <mxGeometry y="346" width="160" height="26" as="geometry" />
        </mxCell>
        <mxCell id="2embDGzhRkxAqKEgTfxS-264" value="User" style="swimlane;fontStyle=1;align=center;verticalAlign=top;childLayout=stackLayout;horizontal=1;startSize=26;horizontalStack=0;resizeParent=1;resizeParentMax=0;resizeLast=0;collapsible=1;marginBottom=0;whiteSpace=wrap;html=1;" vertex="1" parent="1">
          <mxGeometry x="1700" width="160" height="658" as="geometry" />
        </mxCell>
        <mxCell id="2embDGzhRkxAqKEgTfxS-265" value="+ id" style="text;strokeColor=none;fillColor=none;align=left;verticalAlign=top;spacingLeft=4;spacingRight=4;overflow=hidden;rotatable=0;points=[[0,0.5],[1,0.5]];portConstraint=eastwest;whiteSpace=wrap;html=1;" vertex="1" parent="2embDGzhRkxAqKEgTfxS-264">
          <mxGeometry y="26" width="160" height="26" as="geometry" />
        </mxCell>
        <mxCell id="2embDGzhRkxAqKEgTfxS-266" value="+ email" style="text;strokeColor=none;fillColor=none;align=left;verticalAlign=top;spacingLeft=4;spacingRight=4;overflow=hidden;rotatable=0;points=[[0,0.5],[1,0.5]];portConstraint=eastwest;whiteSpace=wrap;html=1;" vertex="1" parent="2embDGzhRkxAqKEgTfxS-264">
          <mxGeometry y="52" width="160" height="26" as="geometry" />
        </mxCell>
        <mxCell id="2embDGzhRkxAqKEgTfxS-267" value="+ roles" style="text;strokeColor=none;fillColor=none;align=left;verticalAlign=top;spacingLeft=4;spacingRight=4;overflow=hidden;rotatable=0;points=[[0,0.5],[1,0.5]];portConstraint=eastwest;whiteSpace=wrap;html=1;" vertex="1" parent="2embDGzhRkxAqKEgTfxS-264">
          <mxGeometry y="78" width="160" height="26" as="geometry" />
        </mxCell>
        <mxCell id="2embDGzhRkxAqKEgTfxS-268" value="+ password" style="text;strokeColor=none;fillColor=none;align=left;verticalAlign=top;spacingLeft=4;spacingRight=4;overflow=hidden;rotatable=0;points=[[0,0.5],[1,0.5]];portConstraint=eastwest;whiteSpace=wrap;html=1;" vertex="1" parent="2embDGzhRkxAqKEgTfxS-264">
          <mxGeometry y="104" width="160" height="26" as="geometry" />
        </mxCell>
        <mxCell id="2embDGzhRkxAqKEgTfxS-269" value="+ username" style="text;strokeColor=none;fillColor=none;align=left;verticalAlign=top;spacingLeft=4;spacingRight=4;overflow=hidden;rotatable=0;points=[[0,0.5],[1,0.5]];portConstraint=eastwest;whiteSpace=wrap;html=1;" vertex="1" parent="2embDGzhRkxAqKEgTfxS-264">
          <mxGeometry y="130" width="160" height="26" as="geometry" />
        </mxCell>
        <mxCell id="2embDGzhRkxAqKEgTfxS-284" value="+ bio" style="text;strokeColor=none;fillColor=none;align=left;verticalAlign=top;spacingLeft=4;spacingRight=4;overflow=hidden;rotatable=0;points=[[0,0.5],[1,0.5]];portConstraint=eastwest;whiteSpace=wrap;html=1;" vertex="1" parent="2embDGzhRkxAqKEgTfxS-264">
          <mxGeometry y="156" width="160" height="26" as="geometry" />
        </mxCell>
        <mxCell id="2embDGzhRkxAqKEgTfxS-285" value="+ isVerified" style="text;strokeColor=none;fillColor=none;align=left;verticalAlign=top;spacingLeft=4;spacingRight=4;overflow=hidden;rotatable=0;points=[[0,0.5],[1,0.5]];portConstraint=eastwest;whiteSpace=wrap;html=1;" vertex="1" parent="2embDGzhRkxAqKEgTfxS-264">
          <mxGeometry y="182" width="160" height="26" as="geometry" />
        </mxCell>
        <mxCell id="2embDGzhRkxAqKEgTfxS-270" value="+ created_at" style="text;strokeColor=none;fillColor=none;align=left;verticalAlign=top;spacingLeft=4;spacingRight=4;overflow=hidden;rotatable=0;points=[[0,0.5],[1,0.5]];portConstraint=eastwest;whiteSpace=wrap;html=1;" vertex="1" parent="2embDGzhRkxAqKEgTfxS-264">
          <mxGeometry y="208" width="160" height="26" as="geometry" />
        </mxCell>
        <mxCell id="2embDGzhRkxAqKEgTfxS-271" value="+ updated_at" style="text;strokeColor=none;fillColor=none;align=left;verticalAlign=top;spacingLeft=4;spacingRight=4;overflow=hidden;rotatable=0;points=[[0,0.5],[1,0.5]];portConstraint=eastwest;whiteSpace=wrap;html=1;" vertex="1" parent="2embDGzhRkxAqKEgTfxS-264">
          <mxGeometry y="234" width="160" height="26" as="geometry" />
        </mxCell>
        <mxCell id="2embDGzhRkxAqKEgTfxS-272" value="" style="line;strokeWidth=1;fillColor=none;align=left;verticalAlign=middle;spacingTop=-1;spacingLeft=3;spacingRight=3;rotatable=0;labelPosition=right;points=[];portConstraint=eastwest;strokeColor=inherit;" vertex="1" parent="2embDGzhRkxAqKEgTfxS-264">
          <mxGeometry y="260" width="160" height="8" as="geometry" />
        </mxCell>
        <mxCell id="2embDGzhRkxAqKEgTfxS-273" value="+ setEmail()" style="text;strokeColor=none;fillColor=none;align=left;verticalAlign=top;spacingLeft=4;spacingRight=4;overflow=hidden;rotatable=0;points=[[0,0.5],[1,0.5]];portConstraint=eastwest;whiteSpace=wrap;html=1;" vertex="1" parent="2embDGzhRkxAqKEgTfxS-264">
          <mxGeometry y="268" width="160" height="26" as="geometry" />
        </mxCell>
        <mxCell id="2embDGzhRkxAqKEgTfxS-274" value="+ setRoles()" style="text;strokeColor=none;fillColor=none;align=left;verticalAlign=top;spacingLeft=4;spacingRight=4;overflow=hidden;rotatable=0;points=[[0,0.5],[1,0.5]];portConstraint=eastwest;whiteSpace=wrap;html=1;" vertex="1" parent="2embDGzhRkxAqKEgTfxS-264">
          <mxGeometry y="294" width="160" height="26" as="geometry" />
        </mxCell>
        <mxCell id="2embDGzhRkxAqKEgTfxS-275" value="+ setPassword()" style="text;strokeColor=none;fillColor=none;align=left;verticalAlign=top;spacingLeft=4;spacingRight=4;overflow=hidden;rotatable=0;points=[[0,0.5],[1,0.5]];portConstraint=eastwest;whiteSpace=wrap;html=1;" vertex="1" parent="2embDGzhRkxAqKEgTfxS-264">
          <mxGeometry y="320" width="160" height="26" as="geometry" />
        </mxCell>
        <mxCell id="2embDGzhRkxAqKEgTfxS-276" value="+ setUsername()" style="text;strokeColor=none;fillColor=none;align=left;verticalAlign=top;spacingLeft=4;spacingRight=4;overflow=hidden;rotatable=0;points=[[0,0.5],[1,0.5]];portConstraint=eastwest;whiteSpace=wrap;html=1;" vertex="1" parent="2embDGzhRkxAqKEgTfxS-264">
          <mxGeometry y="346" width="160" height="26" as="geometry" />
        </mxCell>
        <mxCell id="2embDGzhRkxAqKEgTfxS-288" value="+ setBio()" style="text;strokeColor=none;fillColor=none;align=left;verticalAlign=top;spacingLeft=4;spacingRight=4;overflow=hidden;rotatable=0;points=[[0,0.5],[1,0.5]];portConstraint=eastwest;whiteSpace=wrap;html=1;" vertex="1" parent="2embDGzhRkxAqKEgTfxS-264">
          <mxGeometry y="372" width="160" height="26" as="geometry" />
        </mxCell>
        <mxCell id="2embDGzhRkxAqKEgTfxS-286" value="+ setIsVerified()" style="text;strokeColor=none;fillColor=none;align=left;verticalAlign=top;spacingLeft=4;spacingRight=4;overflow=hidden;rotatable=0;points=[[0,0.5],[1,0.5]];portConstraint=eastwest;whiteSpace=wrap;html=1;" vertex="1" parent="2embDGzhRkxAqKEgTfxS-264">
          <mxGeometry y="398" width="160" height="26" as="geometry" />
        </mxCell>
        <mxCell id="2embDGzhRkxAqKEgTfxS-287" value="+ addArtwork()" style="text;strokeColor=none;fillColor=none;align=left;verticalAlign=top;spacingLeft=4;spacingRight=4;overflow=hidden;rotatable=0;points=[[0,0.5],[1,0.5]];portConstraint=eastwest;whiteSpace=wrap;html=1;" vertex="1" parent="2embDGzhRkxAqKEgTfxS-264">
          <mxGeometry y="424" width="160" height="26" as="geometry" />
        </mxCell>
        <mxCell id="2embDGzhRkxAqKEgTfxS-279" value="+ addComment()" style="text;strokeColor=none;fillColor=none;align=left;verticalAlign=top;spacingLeft=4;spacingRight=4;overflow=hidden;rotatable=0;points=[[0,0.5],[1,0.5]];portConstraint=eastwest;whiteSpace=wrap;html=1;" vertex="1" parent="2embDGzhRkxAqKEgTfxS-264">
          <mxGeometry y="450" width="160" height="26" as="geometry" />
        </mxCell>
        <mxCell id="2embDGzhRkxAqKEgTfxS-280" value="+ addOrder()" style="text;strokeColor=none;fillColor=none;align=left;verticalAlign=top;spacingLeft=4;spacingRight=4;overflow=hidden;rotatable=0;points=[[0,0.5],[1,0.5]];portConstraint=eastwest;whiteSpace=wrap;html=1;" vertex="1" parent="2embDGzhRkxAqKEgTfxS-264">
          <mxGeometry y="476" width="160" height="26" as="geometry" />
        </mxCell>
        <mxCell id="2embDGzhRkxAqKEgTfxS-281" value="+ addMessage()" style="text;strokeColor=none;fillColor=none;align=left;verticalAlign=top;spacingLeft=4;spacingRight=4;overflow=hidden;rotatable=0;points=[[0,0.5],[1,0.5]];portConstraint=eastwest;whiteSpace=wrap;html=1;" vertex="1" parent="2embDGzhRkxAqKEgTfxS-264">
          <mxGeometry y="502" width="160" height="26" as="geometry" />
        </mxCell>
        <mxCell id="2embDGzhRkxAqKEgTfxS-282" value="+ addConversation()" style="text;strokeColor=none;fillColor=none;align=left;verticalAlign=top;spacingLeft=4;spacingRight=4;overflow=hidden;rotatable=0;points=[[0,0.5],[1,0.5]];portConstraint=eastwest;whiteSpace=wrap;html=1;" vertex="1" parent="2embDGzhRkxAqKEgTfxS-264">
          <mxGeometry y="528" width="160" height="26" as="geometry" />
        </mxCell>
        <mxCell id="2embDGzhRkxAqKEgTfxS-283" value="+ addLike()" style="text;strokeColor=none;fillColor=none;align=left;verticalAlign=top;spacingLeft=4;spacingRight=4;overflow=hidden;rotatable=0;points=[[0,0.5],[1,0.5]];portConstraint=eastwest;whiteSpace=wrap;html=1;" vertex="1" parent="2embDGzhRkxAqKEgTfxS-264">
          <mxGeometry y="554" width="160" height="26" as="geometry" />
        </mxCell>
        <mxCell id="2embDGzhRkxAqKEgTfxS-289" value="+ addArtistOrder()" style="text;strokeColor=none;fillColor=none;align=left;verticalAlign=top;spacingLeft=4;spacingRight=4;overflow=hidden;rotatable=0;points=[[0,0.5],[1,0.5]];portConstraint=eastwest;whiteSpace=wrap;html=1;" vertex="1" parent="2embDGzhRkxAqKEgTfxS-264">
          <mxGeometry y="580" width="160" height="26" as="geometry" />
        </mxCell>
        <mxCell id="2embDGzhRkxAqKEgTfxS-277" value="+ onPrePresist()" style="text;strokeColor=none;fillColor=none;align=left;verticalAlign=top;spacingLeft=4;spacingRight=4;overflow=hidden;rotatable=0;points=[[0,0.5],[1,0.5]];portConstraint=eastwest;whiteSpace=wrap;html=1;" vertex="1" parent="2embDGzhRkxAqKEgTfxS-264">
          <mxGeometry y="606" width="160" height="26" as="geometry" />
        </mxCell>
        <mxCell id="2embDGzhRkxAqKEgTfxS-278" value="+ onPreUpdate()" style="text;strokeColor=none;fillColor=none;align=left;verticalAlign=top;spacingLeft=4;spacingRight=4;overflow=hidden;rotatable=0;points=[[0,0.5],[1,0.5]];portConstraint=eastwest;whiteSpace=wrap;html=1;" vertex="1" parent="2embDGzhRkxAqKEgTfxS-264">
          <mxGeometry y="632" width="160" height="26" as="geometry" />
        </mxCell>
      </root>
    </mxGraphModel>
  </diagram>
</mxfile>
